Workbook

Sheet General_Ledger_Data
A1: Txn_ID | B1: Posting_Date | C1: GL_Account | D1: Vendor_ID | E1: Quantity_Units | F1: Unit_Price_USD | G1: Raw_Extended_Cost | H1: Target_Subledger_Balance
A2: TXN-1001 | B2: 46023 | C2: 6001-OPEX | D2: VEND-801 | E2: 150 | F2: 45 | G2: 6750 | H2: 6750
A3: TXN-1002 | B3: 46023 | C3: 6002-CAPEX | D3: VEND-999 | E3: 80 | F3: #N/A | G3: #N/A | H3: 3200
A4: TXN-1003 | B4: 46024 | C4: 6001-OPEX | D4: VEND-803 | E4: 0 | F4: 120 | G4: #DIV/0! | H4: 0
A5: TXN-1004 | B5: 46024 | C5: 6003-SUPPLY | D5: VEND-804 | E5: 200 | F5: $15.50 | G5: 3100 | H5: 3100
A6: TXN-1005 | B6: 46025 | C6: 6001-OPEX | D6: VEND-805 | E6: 50 | F6: 310 | G6: 15500 | H6: 15500
A7: TXN-1006 | B7: 46025 | C7: 6004-TRAVEL | D7: VEND-806 | E7: INVALID_QTY | F7: 75 | G7: #VALUE! | H7: 1875
A8: TXN-1007 | B8: 46026 | C8: 6002-CAPEX | D8: VEND-807 | E8: 120 | F8: 95 | G8: 11400 | H8: 11400
A9: TXN-1008 | B9: 46026 | C9: 6003-SUPPLY | D9: VEND-808 | E9: 300 | F9: 0 | G9: #DIV/0! | H9: 0
A10: TXN-1009 | B10: 46027 | C10: 6001-OPEX | D10: VEND-999 | E10: 45 | F10: #N/A | G10: #N/A | H10: 1800
A11: TXN-1010 | B11: 46027 | C11: 6004-TRAVEL | D11: VEND-810 | E11: 500 | F11: 12.5 | G11: 6250 | H11: 6250
A12: TXN-1011 | B12: 46028 | C12: 6001-OPEX | D12: VEND-811 | E12: 75 | F12: 60 | G12: 4500 | H12: 4500
A13: TXN-1012 | B13: 46028 | C13: 6002-CAPEX | D13: VEND-812 | E13: 10 | F13: 1250 | G13: 12500 | H13: 12500.05
A14: TXN-1013 | B14: 46029 | C14: 6003-SUPPLY | D14: VEND-999 | E14: #N/A | F14: 45 | G14: #N/A | H14: 450
A15: TXN-1014 | B15: 46029 | C15: 6001-OPEX | D15: VEND-814 | E15: 220 | F15: $22.75 | G15: 5005 | H15: 5005
A16: TXN-1015 | B16: 46030 | C16: 6004-TRAVEL | D16: VEND-815 | E16: 15 | F16: 320 | G16: 4800 | H16: 4800
A17: TXN-1016 | B17: 46030 | C17: 6001-OPEX | D17: VEND-816 | E17: 90 | F17: ABC | G17: #VALUE! | H17: 2700
A18: TXN-1017 | B18: 46031 | C18: 6002-CAPEX | D18: VEND-817 | E18: 400 | F18: 18 | G18: 7200 | H18: 7200
A19: TXN-1018 | B19: 46031 | C19: 6003-SUPPLY | D19: VEND-818 | E19: 0 | F19: 55 | G19: #DIV/0! | H19: 0
A20: TXN-1019 | B20: 46032 | C20: 6001-OPEX | D20: VEND-999 | E20: 110 | F20: #N/A | G20: #N/A | H20: 3300
A21: TXN-1020 | B21: 46032 | C21: 6004-TRAVEL | D21: VEND-820 | E21: 60 | F21: 145 | G21: 8700 | H21: 8700
A22: TXN-1021 | B22: 46033 | C22: 6001-OPEX | D22: VEND-821 | E22: 300 | F22: 14 | G22: 4200 | H22: 4200
A23: TXN-1022 | B23: 46033 | C23: 6002-CAPEX | D23: VEND-822 | E23: 25 | F23: 450 | G23: 11250 | H23: 11250
A24: TXN-1023 | B24: 46034 | C24: 6003-SUPPLY | D24: VEND-823 | E24: 180 | F24: $35.00 | G24: 6300 | H24: 6300
A25: TXN-1024 | B25: 46034 | C25: 6001-OPEX | D25: VEND-824 | E25: ERR | F25: 90 | G25: #VALUE! | H25: 4500
A26: TXN-1025 | B26: 46035 | C26: 6004-TRAVEL | D26: VEND-825 | E26: 45 | F26: 210 | G26: 9450 | H26: 9450
A27: TXN-1026 | B27: 46035 | C27: 6001-OPEX | D27: VEND-999 | E27: 500 | F27: #N/A | G27: #N/A | H27: 10000
A28: TXN-1027 | B28: 46036 | C28: 6002-CAPEX | D28: VEND-827 | E28: 85 | F28: 180 | G28: 15300 | H28: 15300
A29: TXN-1028 | B29: 46036 | C29: 6003-SUPPLY | D29: VEND-828 | E29: 0 | F29: 85 | G29: #DIV/0! | H29: 0
A30: TXN-1029 | B30: 46037 | C30: 6001-OPEX | D30: VEND-829 | E30: 135 | F30: 50 | G30: 6750 | H30: 6750
A31: TXN-1030 | B31: 46037 | C31: 6004-TRAVEL | D31: VEND-830 | E31: 70 | F31: $110.00 | G31: 7700 | H31: 7700
A32: TXN-1031 | B32: 46038 | C32: 6001-OPEX | D32: VEND-831 | E32: 160 | F32: 42 | G32: 6720 | H32: 6720
A33: TXN-1032 | B33: 46038 | C33: 6002-CAPEX | D33: VEND-832 | E33: 95 | F33: 310 | G33: 29450 | H33: 29450
A34: TXN-1033 | B34: 46039 | C34: 6003-SUPPLY | D34: VEND-999 | E34: #N/A | F34: 15 | G34: #N/A | H34: 300
A35: TXN-1034 | B35: 46039 | C35: 6001-OPEX | D35: VEND-834 | E35: 210 | F35: 65 | G35: 13650 | H35: 13650
A36: TXN-1035 | B36: 46040 | C36: 6004-TRAVEL | D36: VEND-835 | E36: 30 | F36: 400 | G36: 12000 | H36: 12000
A37: TXN-1036 | B37: 46040 | C37: 6001-OPEX | D37: VEND-836 | E37: 115 | F37: N/A_PRICE | G37: #VALUE! | H37: 5750
A38: TXN-1037 | B38: 46041 | C38: 6002-CAPEX | D38: VEND-837 | E38: 350 | F38: 22 | G38: 7700 | H38: 7700
A39: TXN-1038 | B39: 46041 | C39: 6003-SUPPLY | D39: VEND-838 | E39: 0 | F39: 45 | G39: #DIV/0! | H39: 0
A40: TXN-1039 | B40: 46042 | C40: 6001-OPEX | D40: VEND-839 | E40: 85 | F40: 125 | G40: 10625 | H40: 10625
A41: TXN-1040 | B41: 46042 | C41: 6004-TRAVEL | D41: VEND-840 | E41: 450 | F41: $8.50 | G41: 3825 | H41: 3825
A42: TXN-1041 | B42: 46043 | C42: 6001-OPEX | D42: VEND-841 | E42: 95 | F42: 75 | G42: 7125 | H42: 7125
A43: TXN-1042 | B43: 46043 | C43: 6002-CAPEX | D43: VEND-842 | E43: 50 | F43: 950 | G43: 47500 | H43: 47500.1
A44: TXN-1043 | B44: 46044 | C44: 6003-SUPPLY | D44: VEND-843 | E44: 240 | F44: 25 | G44: 6000 | H44: 6000
A45: TXN-1044 | B45: 46044 | C45: 6001-OPEX | D45: VEND-844 | E45: BAD_QTY | F45: 60 | G45: #VALUE! | H45: 3600
A46: TXN-1045 | B46: 46045 | C46: 6004-TRAVEL | D46: VEND-845 | E46: 18 | F46: 550 | G46: 9900 | H46: 9900
A47: TXN-1046 | B47: 46045 | C47: 6001-OPEX | D47: VEND-999 | E47: #N/A | F47: #N/A | G47: #N/A | H47: 4200
A48: TXN-1047 | B48: 46046 | C48: 6002-CAPEX | D48: VEND-847 | E48: 105 | F48: 140 | G48: 14700 | H48: 14700
A49: TXN-1048 | B49: 46046 | C49: 6003-SUPPLY | D49: VEND-848 | E49: 0 | F49: 130 | G49: #DIV/0! | H49: 0
A50: TXN-1049 | B50: 46047 | C50: 6001-OPEX | D50: VEND-849 | E50: 125 | F50: 80 | G50: 10000 | H50: 10000
A51: TXN-1050 | B51: 46047 | C51: 6004-TRAVEL | D51: VEND-850 | E51: 320 | F51: $18.25 | G51: 5840 | H51: 5840
A52: TXN-1051 | B52: 46048 | C52: 6001-OPEX | D52: VEND-851 | E52: 140 | F52: 55 | G52: 7700 | H52: 7700
A53: TXN-1052 | B53: 46048 | C53: 6002-CAPEX | D53: VEND-852 | E53: 75 | F53: 420 | G53: 31500 | H53: 31500
A54: TXN-1053 | B54: 46049 | C54: 6003-SUPPLY | D54: VEND-853 | E54: 190 | F54: 30 | G54: 5700 | H54: 5700
A55: TXN-1054 | B55: 46049 | C55: 6001-OPEX | D55: VEND-854 | E55: INVALID | F55: 85 | G55: #VALUE! | H55: 5100
A56: TXN-1055 | B56: 46050 | C56: 6004-TRAVEL | D56: VEND-855 | E56: 55 | F56: 290 | G56: 15950 | H56: 15950
A57: TXN-1056 | B57: 46050 | C57: 6001-OPEX | D57: VEND-999 | E57: 400 | F57: #N/A | G57: #N/A | H57: 8000
A58: TXN-1057 | B58: 46051 | C58: 6002-CAPEX | D58: VEND-857 | E58: 110 | F58: 165 | G58: 18150 | H58: 18150
A59: TXN-1058 | B59: 46051 | C59: 6003-SUPPLY | D59: VEND-858 | E59: 0 | F59: 95 | G59: #DIV/0! | H59: 0
A60: TXN-1059 | B60: 46052 | C60: 6001-OPEX | D60: VEND-859 | E60: 165 | F60: 48 | G60: 7920 | H60: 7920
A61: TXN-1060 | B61: 46052 | C61: 6004-TRAVEL | D61: VEND-860 | E61: 280 | F61: $14.50 | G61: 4060 | H61: 4060
A62: TXN-1061 | B62: 46053 | C62: 6001-OPEX | D62: VEND-861 | E62: 115 | F62: 62 | G62: 7130 | H62: 7130
A63: TXN-1062 | B63: 46053 | C63: 6002-CAPEX | D63: VEND-862 | E63: 60 | F63: 850 | G63: 51000 | H63: 51000.08
A64: TXN-1063 | B64: 46054 | C64: 6003-SUPPLY | D64: VEND-999 | E64: #N/A | F64: 22 | G64: #N/A | H64: 440
A65: TXN-1064 | B65: 46054 | C65: 6001-OPEX | D65: VEND-864 | E65: 175 | F65: $40.00 | G65: 7000 | H65: 7000
A66: TXN-1065 | B66: 46055 | C66: 6004-TRAVEL | D66: VEND-865 | E66: 25 | F66: 380 | G66: 9500 | H66: 9500
A67: TXN-1066 | B67: 46055 | C67: 6001-OPEX | D67: VEND-866 | E67: 80 | F67: NULL_VAL | G67: #VALUE! | H67: 3200
A68: TXN-1067 | B68: 46056 | C68: 6002-CAPEX | D68: VEND-867 | E68: 290 | F68: 24 | G68: 6960 | H68: 6960
A69: TXN-1068 | B69: 46056 | C69: 6003-SUPPLY | D69: VEND-868 | E69: 0 | F69: 60 | G69: #DIV/0! | H69: 0
A70: TXN-1069 | B70: 46057 | C70: 6001-OPEX | D70: VEND-999 | E70: 100 | F70: #N/A | G70: #N/A | H70: 4000
A71: TXN-1070 | B71: 46057 | C71: 6004-TRAVEL | D71: VEND-870 | E71: 350 | F71: 16.5 | G71: 5775 | H71: 5775
A72: TXN-1071 | B72: 46058 | C72: 6001-OPEX | D72: VEND-871 | E72: 130 | F72: 52 | G72: 6760 | H72: 6760
A73: TXN-1072 | B73: 46058 | C73: 6002-CAPEX | D73: VEND-872 | E73: 45 | F73: 520 | G73: 23400 | H73: 23400
A74: TXN-1073 | B74: 46059 | C74: 6003-SUPPLY | D74: VEND-873 | E74: 210 | F74: $28.00 | G74: 5880 | H74: 5880
A75: TXN-1074 | B75: 46059 | C75: 6001-OPEX | D75: VEND-874 | E75: ERR_QTY | F75: 70 | G75: #VALUE! | H75: 4200
A76: TXN-1075 | B76: 46060 | C76: 6004-TRAVEL | D76: VEND-875 | E76: 35 | F76: 310 | G76: 10850 | H76: 10850
A77: TXN-1076 | B77: 46060 | C77: 6001-OPEX | D77: VEND-999 | E77: 300 | F77: #N/A | G77: #N/A | H77: 6000
A78: TXN-1077 | B78: 46061 | C78: 6002-CAPEX | D78: VEND-877 | E78: 95 | F78: 195 | G78: 18525 | H78: 18525
A79: TXN-1078 | B79: 46061 | C79: 6003-SUPPLY | D79: VEND-878 | E79: 0 | F79: 110 | G79: #DIV/0! | H79: 0
A80: TXN-1079 | B80: 46062 | C80: 6001-OPEX | D80: VEND-879 | E80: 145 | F80: 58 | G80: 8410 | H80: 8410
A81: TXN-1080 | B81: 46062 | C81: 6004-TRAVEL | D81: VEND-880 | E81: 220 | F81: $21.00 | G81: 4620 | H81: 4620
A82: TXN-1081 | B82: 46063 | C82: 6001-OPEX | D82: VEND-881 | E82: 180 | F82: 38 | G82: 6840 | H82: 6840
A83: TXN-1082 | B83: 46063 | C83: 6002-CAPEX | D83: VEND-882 | E83: 85 | F83: 340 | G83: 28900 | H83: 28900
A84: TXN-1083 | B84: 46064 | C84: 6003-SUPPLY | D84: VEND-999 | E84: #N/A | F84: 40 | G84: #N/A | H84: 800
A85: TXN-1084 | B85: 46064 | C85: 6001-OPEX | D85: VEND-884 | E85: 250 | F85: 45 | G85: 11250 | H85: 11250
A86: TXN-1085 | B86: 46065 | C86: 6004-TRAVEL | D86: VEND-885 | E86: 40 | F86: 275 | G86: 11000 | H86: 11000
A87: TXN-1086 | B87: 46065 | C87: 6001-OPEX | D87: VEND-886 | E87: 70 | F87: BAD_PRC | G87: #VALUE! | H87: 3500
A88: TXN-1087 | B88: 46066 | C88: 6002-CAPEX | D88: VEND-887 | E88: 310 | F88: 20 | G88: 6200 | H88: 6200
A89: TXN-1088 | B89: 46066 | C89: 6003-SUPPLY | D89: VEND-888 | E89: 0 | F89: 75 | G89: #DIV/0! | H89: 0
A90: TXN-1089 | B90: 46067 | C90: 6001-OPEX | D90: VEND-890 | E90: 90 | F90: 110 | G90: 9900 | H90: 9900
A91: TXN-1090 | B91: 46067 | C91: 6004-TRAVEL | D91: VEND-891 | E91: 410 | F91: $10.00 | G91: 4100 | H91: 4100
A92: TXN-1091 | B92: 46068 | C92: 6001-OPEX | D92: VEND-892 | E92: 105 | F92: 68 | G92: 7140 | H92: 7140
A93: TXN-1092 | B93: 46068 | C93: 6002-CAPEX | D93: VEND-893 | E93: 55 | F93: 680 | G93: 37400 | H93: 37400.12
A94: TXN-1093 | B94: 46069 | C94: 6003-SUPPLY | D94: VEND-894 | E94: 175 | F94: 32 | G94: 5600 | H94: 5600
A95: TXN-1094 | B95: 46069 | C95: 6001-OPEX | D95: VEND-895 | E95: ERR | F95: 50 | G95: #VALUE! | H95: 2500
A96: TXN-1095 | B96: 46070 | C96: 6004-TRAVEL | D96: VEND-896 | E96: 20 | F96: 490 | G96: 9800 | H96: 9800
A97: TXN-1096 | B97: 46070 | C97: 6001-OPEX | D97: VEND-999 | E97: 250 | F97: #N/A | G97: #N/A | H97: 5000
A98: TXN-1097 | B98: 46071 | C98: 6002-CAPEX | D98: VEND-898 | E98: 115 | F98: 150 | G98: 17250 | H98: 17250
A99: TXN-1098 | B99: 46071 | C99: 6003-SUPPLY | D99: VEND-899 | E99: 0 | F99: 140 | G99: #DIV/0! | H99: 0
A100: TXN-1099 | B100: 46072 | C100: 6001-OPEX | D100: VEND-900 | E100: 140 | F100: 55 | G100: 7700 | H100: 7700
...

Sheet Formula_Repair_Engine
A1: Txn_ID | B1: Posting_Date | C1: GL_Account | D1: Vendor_ID | E1: Clean_Quantity | F1: Clean_Unit_Price | G1: Repaired_Extended_Cost | H1: Repair_Audit_Status
A2: =General_Ledger_Data!A2 -> TXN-1001 | B2: =General_Ledger_Data!B2 -> 46023 | C2: =General_Ledger_Data!C2 -> 6001-OPEX | D2: =IF(OR(ISBLANK(General_Ledger_Data!D2), General_Ledger_Data!D2="#N/A"), "VEND-UNKNOWN", General_Ledger_Data!D2) -> VEND-801 | E2: =IFERROR(__xludf.DUMMYFUNCTION("IFERROR(VALUE(REGEXREPLACE(TO_TEXT(General_Ledger_Data!E2), ""[^0-9.]"", """")), 0)"),150.0) -> 150 | F2: =IFERROR(__xludf.DUMMYFUNCTION("IFERROR(VALUE(REGEXREPLACE(TO_TEXT(General_Ledger_Data!F2), ""[^0-9.]"", """")), 0)"),45.0) -> 45 | G2: =IF(OR(E2=0, F2=0), 0, E2*F2) -> 6750 | H2: =IF(ISNUMBER(General_Ledger_Data!G2), "PASSED CLEAN", "REPAIRED") -> PASSED CLEAN
A3: =General_Ledger_Data!A3 -> TXN-1002 | B3: =General_Ledger_Data!B3 -> 46023 | C3: =General_Ledger_Data!C3 -> 6002-CAPEX | D3: =IF(OR(ISBLANK(General_Ledger_Data!D3), General_Ledger_Data!D3="#N/A"), "VEND-UNKNOWN", General_Ledger_Data!D3) -> VEND-999 | E3: =IFERROR(__xludf.DUMMYFUNCTION("IFERROR(VALUE(REGEXREPLACE(TO_TEXT(General_Ledger_Data!E3), ""[^0-9.]"", """")), 0)"),80.0) -> 80 | F3: =IFERROR(__xludf.DUMMYFUNCTION("IFERROR(VALUE(REGEXREPLACE(TO_TEXT(General_Ledger_Data!F3), ""[^0-9.]"", """")), 0)"),0.0) -> 0 | G3: =IF(OR(E3=0, F3=0), 0, E3*F3) -> 0 | H3: =IF(ISNUMBER(General_Ledger_Data!G3), "PASSED CLEAN", "REPAIRED") -> REPAIRED
A4: =General_Ledger_Data!A4 -> TXN-1003 | B4: =General_Ledger_Data!B4 -> 46024 | C4: =General_Ledger_Data!C4 -> 6001-OPEX | D4: =IF(OR(ISBLANK(General_Ledger_Data!D4), General_Ledger_Data!D4="#N/A"), "VEND-UNKNOWN", General_Ledger_Data!D4) -> VEND-803 | E4: =IFERROR(__xludf.DUMMYFUNCTION("IFERROR(VALUE(REGEXREPLACE(TO_TEXT(General_Ledger_Data!E4), ""[^0-9.]"", """")), 0)"),0.0) -> 0 | F4: =IFERROR(__xludf.DUMMYFUNCTION("IFERROR(VALUE(REGEXREPLACE(TO_TEXT(General_Ledger_Data!F4), ""[^0-9.]"", """")), 0)"),120.0) -> 120 | G4: =IF(OR(E4=0, F4=0), 0, E4*F4) -> 0 | H4: =IF(ISNUMBER(General_Ledger_Data!G4), "PASSED CLEAN", "REPAIRED") -> REPAIRED
A5: =General_Ledger_Data!A5 -> TXN-1004 | B5: =General_Ledger_Data!B5 -> 46024 | C5: =General_Ledger_Data!C5 -> 6003-SUPPLY | D5: =IF(OR(ISBLANK(General_Ledger_Data!D5), General_Ledger_Data!D5="#N/A"), "VEND-UNKNOWN", General_Ledger_Data!D5) -> VEND-804 | E5: =IFERROR(__xludf.DUMMYFUNCTION("IFERROR(VALUE(REGEXREPLACE(TO_TEXT(General_Ledger_Data!E5), ""[^0-9.]"", """")), 0)"),200.0) -> 200 | F5: =IFERROR(__xludf.DUMMYFUNCTION("IFERROR(VALUE(REGEXREPLACE(TO_TEXT(General_Ledger_Data!F5), ""[^0-9.]"", """")), 0)"),15.5) -> 15.5 | G5: =IF(OR(E5=0, F5=0), 0, E5*F5) -> 3100 | H5: =IF(ISNUMBER(General_Ledger_Data!G5), "PASSED CLEAN", "REPAIRED") -> PASSED CLEAN
A6: =General_Ledger_Data!A6 -> TXN-1005 | B6: =General_Ledger_Data!B6 -> 46025 | C6: =General_Ledger_Data!C6 -> 6001-OPEX | D6: =IF(OR(ISBLANK(General_Ledger_Data!D6), General_Ledger_Data!D6="#N/A"), "VEND-UNKNOWN", General_Ledger_Data!D6) -> VEND-805 | E6: =IFERROR(__xludf.DUMMYFUNCTION("IFERROR(VALUE(REGEXREPLACE(TO_TEXT(General_Ledger_Data!E6), ""[^0-9.]"", """")), 0)"),50.0) -> 50 | F6: =IFERROR(__xludf.DUMMYFUNCTION("IFERROR(VALUE(REGEXREPLACE(TO_TEXT(General_Ledger_Data!F6), ""[^0-9.]"", """")), 0)"),310.0) -> 310 | G6: =IF(OR(E6=0, F6=0), 0, E6*F6) -> 15500 | H6: =IF(ISNUMBER(General_Ledger_Data!G6), "PASSED CLEAN", "REPAIRED") -> PASSED CLEAN
A7: =General_Ledger_Data!A7 -> TXN-1006 | B7: =General_Ledger_Data!B7 -> 46025 | C7: =General_Ledger_Data!C7 -> 6004-TRAVEL | D7: =IF(OR(ISBLANK(General_Ledger_Data!D7), General_Ledger_Data!D7="#N/A"), "VEND-UNKNOWN", General_Ledger_Data!D7) -> VEND-806 | E7: =IFERROR(__xludf.DUMMYFUNCTION("IFERROR(VALUE(REGEXREPLACE(TO_TEXT(General_Ledger_Data!E7), ""[^0-9.]"", """")), 0)"),0.0) -> 0 | F7: =IFERROR(__xludf.DUMMYFUNCTION("IFERROR(VALUE(REGEXREPLACE(TO_TEXT(General_Ledger_Data!F7), ""[^0-9.]"", """")), 0)"),75.0) -> 75 | G7: =IF(OR(E7=0, F7=0), 0, E7*F7) -> 0 | H7: =IF(ISNUMBER(General_Ledger_Data!G7), "PASSED CLEAN", "REPAIRED") -> REPAIRED
A8: =General_Ledger_Data!A8 -> TXN-1007 | B8: =General_Ledger_Data!B8 -> 46026 | C8: =General_Ledger_Data!C8 -> 6002-CAPEX | D8: =IF(OR(ISBLANK(General_Ledger_Data!D8), General_Ledger_Data!D8="#N/A"), "VEND-UNKNOWN", General_Ledger_Data!D8) -> VEND-807 | E8: =IFERROR(__xludf.DUMMYFUNCTION("IFERROR(VALUE(REGEXREPLACE(TO_TEXT(General_Ledger_Data!E8), ""[^0-9.]"", """")), 0)"),120.0) -> 120 | F8: =IFERROR(__xludf.DUMMYFUNCTION("IFERROR(VALUE(REGEXREPLACE(TO_TEXT(General_Ledger_Data!F8), ""[^0-9.]"", """")), 0)"),95.0) -> 95 | G8: =IF(OR(E8=0, F8=0), 0, E8*F8) -> 11400 | H8: =IF(ISNUMBER(General_Ledger_Data!G8), "PASSED CLEAN", "REPAIRED") -> PASSED CLEAN
A9: =General_Ledger_Data!A9 -> TXN-1008 | B9: =General_Ledger_Data!B9 -> 46026 | C9: =General_Ledger_Data!C9 -> 6003-SUPPLY | D9: =IF(OR(ISBLANK(General_Ledger_Data!D9), General_Ledger_Data!D9="#N/A"), "VEND-UNKNOWN", General_Ledger_Data!D9) -> VEND-808 | E9: =IFERROR(__xludf.DUMMYFUNCTION("IFERROR(VALUE(REGEXREPLACE(TO_TEXT(General_Ledger_Data!E9), ""[^0-9.]"", """")), 0)"),300.0) -> 300 | F9: =IFERROR(__xludf.DUMMYFUNCTION("IFERROR(VALUE(REGEXREPLACE(TO_TEXT(General_Ledger_Data!F9), ""[^0-9.]"", """")), 0)"),0.0) -> 0 | G9: =IF(OR(E9=0, F9=0), 0, E9*F9) -> 0 | H9: =IF(ISNUMBER(General_Ledger_Data!G9), "PASSED CLEAN", "REPAIRED") -> REPAIRED
A10: =General_Ledger_Data!A10 -> TXN-1009 | B10: =General_Ledger_Data!B10 -> 46027 | C10: =General_Ledger_Data!C10 -> 6001-OPEX | D10: =IF(OR(ISBLANK(General_Ledger_Data!D10), General_Ledger_Data!D10="#N/A"), "VEND-UNKNOWN", General_Ledger_Data!D10) -> VEND-999 | E10: =IFERROR(__xludf.DUMMYFUNCTION("IFERROR(VALUE(REGEXREPLACE(TO_TEXT(General_Ledger_Data!E10), ""[^0-9.]"", """")), 0)"),45.0) -> 45 | F10: =IFERROR(__xludf.DUMMYFUNCTION("IFERROR(VALUE(REGEXREPLACE(TO_TEXT(General_Ledger_Data!F10), ""[^0-9.]"", """")), 0)"),0.0) -> 0 | G10: =IF(OR(E10=0, F10=0), 0, E10*F10) -> 0 | H10: =IF(ISNUMBER(General_Ledger_Data!G10), "PASSED CLEAN", "REPAIRED") -> REPAIRED
A11: =General_Ledger_Data!A11 -> TXN-1010 | B11: =General_Ledger_Data!B11 -> 46027 | C11: =General_Ledger_Data!C11 -> 6004-TRAVEL | D11: =IF(OR(ISBLANK(General_Ledger_Data!D11), General_Ledger_Data!D11="#N/A"), "VEND-UNKNOWN", General_Ledger_Data!D11) -> VEND-810 | E11: =IFERROR(__xludf.DUMMYFUNCTION("IFERROR(VALUE(REGEXREPLACE(TO_TEXT(General_Ledger_Data!E11), ""[^0-9.]"", """")), 0)"),500.0) -> 500 | F11: =IFERROR(__xludf.DUMMYFUNCTION("IFERROR(VALUE(REGEXREPLACE(TO_TEXT(General_Ledger_Data!F11), ""[^0-9.]"", """")), 0)"),12.5) -> 12.5 | G11: =IF(OR(E11=0, F11=0), 0, E11*F11) -> 6250 | H11: =IF(ISNUMBER(General_Ledger_Data!G11), "PASSED CLEAN", "REPAIRED") -> PASSED CLEAN
A12: =General_Ledger_Data!A12 -> TXN-1011 | B12: =General_Ledger_Data!B12 -> 46028 | C12: =General_Ledger_Data!C12 -> 6001-OPEX | D12: =IF(OR(ISBLANK(General_Ledger_Data!D12), General_Ledger_Data!D12="#N/A"), "VEND-UNKNOWN", General_Ledger_Data!D12) -> VEND-811 | E12: =IFERROR(__xludf.DUMMYFUNCTION("IFERROR(VALUE(REGEXREPLACE(TO_TEXT(General_Ledger_Data!E12), ""[^0-9.]"", """")), 0)"),75.0) -> 75 | F12: =IFERROR(__xludf.DUMMYFUNCTION("IFERROR(VALUE(REGEXREPLACE(TO_TEXT(General_Ledger_Data!F12), ""[^0-9.]"", """")), 0)"),60.0) -> 60 | G12: =IF(OR(E12=0, F12=0), 0, E12*F12) -> 4500 | H12: =IF(ISNUMBER(General_Ledger_Data!G12), "PASSED CLEAN", "REPAIRED") -> PASSED CLEAN
A13: =General_Ledger_Data!A13 -> TXN-1012 | B13: =General_Ledger_Data!B13 -> 46028 | C13: =General_Ledger_Data!C13 -> 6002-CAPEX | D13: =IF(OR(ISBLANK(General_Ledger_Data!D13), General_Ledger_Data!D13="#N/A"), "VEND-UNKNOWN", General_Ledger_Data!D13) -> VEND-812 | E13: =IFERROR(__xludf.DUMMYFUNCTION("IFERROR(VALUE(REGEXREPLACE(TO_TEXT(General_Ledger_Data!E13), ""[^0-9.]"", """")), 0)"),10.0) -> 10 | F13: =IFERROR(__xludf.DUMMYFUNCTION("IFERROR(VALUE(REGEXREPLACE(TO_TEXT(General_Ledger_Data!F13), ""[^0-9.]"", """")), 0)"),1250.0) -> 1250 | G13: =IF(OR(E13=0, F13=0), 0, E13*F13) -> 12500 | H13: =IF(ISNUMBER(General_Ledger_Data!G13), "PASSED CLEAN", "REPAIRED") -> PASSED CLEAN
A14: =General_Ledger_Data!A14 -> TXN-1013 | B14: =General_Ledger_Data!B14 -> 46029 | C14: =General_Ledger_Data!C14 -> 6003-SUPPLY | D14: =IF(OR(ISBLANK(General_Ledger_Data!D14), General_Ledger_Data!D14="#N/A"), "VEND-UNKNOWN", General_Ledger_Data!D14) -> VEND-999 | E14: =IFERROR(__xludf.DUMMYFUNCTION("IFERROR(VALUE(REGEXREPLACE(TO_TEXT(General_Ledger_Data!E14), ""[^0-9.]"", """")), 0)"),0.0) -> 0 | F14: =IFERROR(__xludf.DUMMYFUNCTION("IFERROR(VALUE(REGEXREPLACE(TO_TEXT(General_Ledger_Data!F14), ""[^0-9.]"", """")), 0)"),45.0) -> 45 | G14: =IF(OR(E14=0, F14=0), 0, E14*F14) -> 0 | H14: =IF(ISNUMBER(General_Ledger_Data!G14), "PASSED CLEAN", "REPAIRED") -> REPAIRED
A15: =General_Ledger_Data!A15 -> TXN-1014 | B15: =General_Ledger_Data!B15 -> 46029 | C15: =General_Ledger_Data!C15 -> 6001-OPEX | D15: =IF(OR(ISBLANK(General_Ledger_Data!D15), General_Ledger_Data!D15="#N/A"), "VEND-UNKNOWN", General_Ledger_Data!D15) -> VEND-814 | E15: =IFERROR(__xludf.DUMMYFUNCTION("IFERROR(VALUE(REGEXREPLACE(TO_TEXT(General_Ledger_Data!E15), ""[^0-9.]"", """")), 0)"),220.0) -> 220 | F15: =IFERROR(__xludf.DUMMYFUNCTION("IFERROR(VALUE(REGEXREPLACE(TO_TEXT(General_Ledger_Data!F15), ""[^0-9.]"", """")), 0)"),22.75) -> 22.75 | G15: =IF(OR(E15=0, F15=0), 0, E15*F15) -> 5005 | H15: =IF(ISNUMBER(General_Ledger_Data!G15), "PASSED CLEAN", "REPAIRED") -> PASSED CLEAN
A16: =General_Ledger_Data!A16 -> TXN-1015 | B16: =General_Ledger_Data!B16 -> 46030 | C16: =General_Ledger_Data!C16 -> 6004-TRAVEL | D16: =IF(OR(ISBLANK(General_Ledger_Data!D16), General_Ledger_Data!D16="#N/A"), "VEND-UNKNOWN", General_Ledger_Data!D16) -> VEND-815 | E16: =IFERROR(__xludf.DUMMYFUNCTION("IFERROR(VALUE(REGEXREPLACE(TO_TEXT(General_Ledger_Data!E16), ""[^0-9.]"", """")), 0)"),15.0) -> 15 | F16: =IFERROR(__xludf.DUMMYFUNCTION("IFERROR(VALUE(REGEXREPLACE(TO_TEXT(General_Ledger_Data!F16), ""[^0-9.]"", """")), 0)"),320.0) -> 320 | G16: =IF(OR(E16=0, F16=0), 0, E16*F16) -> 4800 | H16: =IF(ISNUMBER(General_Ledger_Data!G16), "PASSED CLEAN", "REPAIRED") -> PASSED CLEAN
A17: =General_Ledger_Data!A17 -> TXN-1016 | B17: =General_Ledger_Data!B17 -> 46030 | C17: =General_Ledger_Data!C17 -> 6001-OPEX | D17: =IF(OR(ISBLANK(General_Ledger_Data!D17), General_Ledger_Data!D17="#N/A"), "VEND-UNKNOWN", General_Ledger_Data!D17) -> VEND-816 | E17: =IFERROR(__xludf.DUMMYFUNCTION("IFERROR(VALUE(REGEXREPLACE(TO_TEXT(General_Ledger_Data!E17), ""[^0-9.]"", """")), 0)"),90.0) -> 90 | F17: =IFERROR(__xludf.DUMMYFUNCTION("IFERROR(VALUE(REGEXREPLACE(TO_TEXT(General_Ledger_Data!F17), ""[^0-9.]"", """")), 0)"),0.0) -> 0 | G17: =IF(OR(E17=0, F17=0), 0, E17*F17) -> 0 | H17: =IF(ISNUMBER(General_Ledger_Data!G17), "PASSED CLEAN", "REPAIRED") -> REPAIRED
A18: =General_Ledger_Data!A18 -> TXN-1017 | B18: =General_Ledger_Data!B18 -> 46031 | C18: =General_Ledger_Data!C18 -> 6002-CAPEX | D18: =IF(OR(ISBLANK(General_Ledger_Data!D18), General_Ledger_Data!D18="#N/A"), "VEND-UNKNOWN", General_Ledger_Data!D18) -> VEND-817 | E18: =IFERROR(__xludf.DUMMYFUNCTION("IFERROR(VALUE(REGEXREPLACE(TO_TEXT(General_Ledger_Data!E18), ""[^0-9.]"", """")), 0)"),400.0) -> 400 | F18: =IFERROR(__xludf.DUMMYFUNCTION("IFERROR(VALUE(REGEXREPLACE(TO_TEXT(General_Ledger_Data!F18), ""[^0-9.]"", """")), 0)"),18.0) -> 18 | G18: =IF(OR(E18=0, F18=0), 0, E18*F18) -> 7200 | H18: =IF(ISNUMBER(General_Ledger_Data!G18), "PASSED CLEAN", "REPAIRED") -> PASSED CLEAN
A19: =General_Ledger_Data!A19 -> TXN-1018 | B19: =General_Ledger_Data!B19 -> 46031 | C19: =General_Ledger_Data!C19 -> 6003-SUPPLY | D19: =IF(OR(ISBLANK(General_Ledger_Data!D19), General_Ledger_Data!D19="#N/A"), "VEND-UNKNOWN", General_Ledger_Data!D19) -> VEND-818 | E19: =IFERROR(__xludf.DUMMYFUNCTION("IFERROR(VALUE(REGEXREPLACE(TO_TEXT(General_Ledger_Data!E19), ""[^0-9.]"", """")), 0)"),0.0) -> 0 | F19: =IFERROR(__xludf.DUMMYFUNCTION("IFERROR(VALUE(REGEXREPLACE(TO_TEXT(General_Ledger_Data!F19), ""[^0-9.]"", """")), 0)"),55.0) -> 55 | G19: =IF(OR(E19=0, F19=0), 0, E19*F19) -> 0 | H19: =IF(ISNUMBER(General_Ledger_Data!G19), "PASSED CLEAN", "REPAIRED") -> REPAIRED
A20: =General_Ledger_Data!A20 -> TXN-1019 | B20: =General_Ledger_Data!B20 -> 46032 | C20: =General_Ledger_Data!C20 -> 6001-OPEX | D20: =IF(OR(ISBLANK(General_Ledger_Data!D20), General_Ledger_Data!D20="#N/A"), "VEND-UNKNOWN", General_Ledger_Data!D20) -> VEND-999 | E20: =IFERROR(__xludf.DUMMYFUNCTION("IFERROR(VALUE(REGEXREPLACE(TO_TEXT(General_Ledger_Data!E20), ""[^0-9.]"", """")), 0)"),110.0) -> 110 | F20: =IFERROR(__xludf.DUMMYFUNCTION("IFERROR(VALUE(REGEXREPLACE(TO_TEXT(General_Ledger_Data!F20), ""[^0-9.]"", """")), 0)"),0.0) -> 0 | G20: =IF(OR(E20=0, F20=0), 0, E20*F20) -> 0 | H20: =IF(ISNUMBER(General_Ledger_Data!G20), "PASSED CLEAN", "REPAIRED") -> REPAIRED
A21: =General_Ledger_Data!A21 -> TXN-1020 | B21: =General_Ledger_Data!B21 -> 46032 | C21: =General_Ledger_Data!C21 -> 6004-TRAVEL | D21: =IF(OR(ISBLANK(General_Ledger_Data!D21), General_Ledger_Data!D21="#N/A"), "VEND-UNKNOWN", General_Ledger_Data!D21) -> VEND-820 | E21: =IFERROR(__xludf.DUMMYFUNCTION("IFERROR(VALUE(REGEXREPLACE(TO_TEXT(General_Ledger_Data!E21), ""[^0-9.]"", """")), 0)"),60.0) -> 60 | F21: =IFERROR(__xludf.DUMMYFUNCTION("IFERROR(VALUE(REGEXREPLACE(TO_TEXT(General_Ledger_Data!F21), ""[^0-9.]"", """")), 0)"),145.0) -> 145 | G21: =IF(OR(E21=0, F21=0), 0, E21*F21) -> 8700 | H21: =IF(ISNUMBER(General_Ledger_Data!G21), "PASSED CLEAN", "REPAIRED") -> PASSED CLEAN
A22: =General_Ledger_Data!A22 -> TXN-1021 | B22: =General_Ledger_Data!B22 -> 46033 | C22: =General_Ledger_Data!C22 -> 6001-OPEX | D22: =IF(OR(ISBLANK(General_Ledger_Data!D22), General_Ledger_Data!D22="#N/A"), "VEND-UNKNOWN", General_Ledger_Data!D22) -> VEND-821 | E22: =IFERROR(__xludf.DUMMYFUNCTION("IFERROR(VALUE(REGEXREPLACE(TO_TEXT(General_Ledger_Data!E22), ""[^0-9.]"", """")), 0)"),300.0) -> 300 | F22: =IFERROR(__xludf.DUMMYFUNCTION("IFERROR(VALUE(REGEXREPLACE(TO_TEXT(General_Ledger_Data!F22), ""[^0-9.]"", """")), 0)"),14.0) -> 14 | G22: =IF(OR(E22=0, F22=0), 0, E22*F22) -> 4200 | H22: =IF(ISNUMBER(General_Ledger_Data!G22), "PASSED CLEAN", "REPAIRED") -> PASSED CLEAN
A23: =General_Ledger_Data!A23 -> TXN-1022 | B23: =General_Ledger_Data!B23 -> 46033 | C23: =General_Ledger_Data!C23 -> 6002-CAPEX | D23: =IF(OR(ISBLANK(General_Ledger_Data!D23), General_Ledger_Data!D23="#N/A"), "VEND-UNKNOWN", General_Ledger_Data!D23) -> VEND-822 | E23: =IFERROR(__xludf.DUMMYFUNCTION("IFERROR(VALUE(REGEXREPLACE(TO_TEXT(General_Ledger_Data!E23), ""[^0-9.]"", """")), 0)"),25.0) -> 25 | F23: =IFERROR(__xludf.DUMMYFUNCTION("IFERROR(VALUE(REGEXREPLACE(TO_TEXT(General_Ledger_Data!F23), ""[^0-9.]"", """")), 0)"),450.0) -> 450 | G23: =IF(OR(E23=0, F23=0), 0, E23*F23) -> 11250 | H23: =IF(ISNUMBER(General_Ledger_Data!G23), "PASSED CLEAN", "REPAIRED") -> PASSED CLEAN
A24: =General_Ledger_Data!A24 -> TXN-1023 | B24: =General_Ledger_Data!B24 -> 46034 | C24: =General_Ledger_Data!C24 -> 6003-SUPPLY | D24: =IF(OR(ISBLANK(General_Ledger_Data!D24), General_Ledger_Data!D24="#N/A"), "VEND-UNKNOWN", General_Ledger_Data!D24) -> VEND-823 | E24: =IFERROR(__xludf.DUMMYFUNCTION("IFERROR(VALUE(REGEXREPLACE(TO_TEXT(General_Ledger_Data!E24), ""[^0-9.]"", """")), 0)"),180.0) -> 180 | F24: =IFERROR(__xludf.DUMMYFUNCTION("IFERROR(VALUE(REGEXREPLACE(TO_TEXT(General_Ledger_Data!F24), ""[^0-9.]"", """")), 0)"),35.0) -> 35 | G24: =IF(OR(E24=0, F24=0), 0, E24*F24) -> 6300 | H24: =IF(ISNUMBER(General_Ledger_Data!G24), "PASSED CLEAN", "REPAIRED") -> PASSED CLEAN
A25: =General_Ledger_Data!A25 -> TXN-1024 | B25: =General_Ledger_Data!B25 -> 46034 | C25: =General_Ledger_Data!C25 -> 6001-OPEX | D25: =IF(OR(ISBLANK(General_Ledger_Data!D25), General_Ledger_Data!D25="#N/A"), "VEND-UNKNOWN", General_Ledger_Data!D25) -> VEND-824 | E25: =IFERROR(__xludf.DUMMYFUNCTION("IFERROR(VALUE(REGEXREPLACE(TO_TEXT(General_Ledger_Data!E25), ""[^0-9.]"", """")), 0)"),0.0) -> 0 | F25: =IFERROR(__xludf.DUMMYFUNCTION("IFERROR(VALUE(REGEXREPLACE(TO_TEXT(General_Ledger_Data!F25), ""[^0-9.]"", """")), 0)"),90.0) -> 90 | G25: =IF(OR(E25=0, F25=0), 0, E25*F25) -> 0 | H25: =IF(ISNUMBER(General_Ledger_Data!G25), "PASSED CLEAN", "REPAIRED") -> REPAIRED
A26: =General_Ledger_Data!A26 -> TXN-1025 | B26: =General_Ledger_Data!B26 -> 46035 | C26: =General_Ledger_Data!C26 -> 6004-TRAVEL | D26: =IF(OR(ISBLANK(General_Ledger_Data!D26), General_Ledger_Data!D26="#N/A"), "VEND-UNKNOWN", General_Ledger_Data!D26) -> VEND-825 | E26: =IFERROR(__xludf.DUMMYFUNCTION("IFERROR(VALUE(REGEXREPLACE(TO_TEXT(General_Ledger_Data!E26), ""[^0-9.]"", """")), 0)"),45.0) -> 45 | F26: =IFERROR(__xludf.DUMMYFUNCTION("IFERROR(VALUE(REGEXREPLACE(TO_TEXT(General_Ledger_Data!F26), ""[^0-9.]"", """")), 0)"),210.0) -> 210 | G26: =IF(OR(E26=0, F26=0), 0, E26*F26) -> 9450 | H26: =IF(ISNUMBER(General_Ledger_Data!G26), "PASSED CLEAN", "REPAIRED") -> PASSED CLEAN
A27: =General_Ledger_Data!A27 -> TXN-1026 | B27: =General_Ledger_Data!B27 -> 46035 | C27: =General_Ledger_Data!C27 -> 6001-OPEX | D27: =IF(OR(ISBLANK(General_Ledger_Data!D27), General_Ledger_Data!D27="#N/A"), "VEND-UNKNOWN", General_Ledger_Data!D27) -> VEND-999 | E27: =IFERROR(__xludf.DUMMYFUNCTION("IFERROR(VALUE(REGEXREPLACE(TO_TEXT(General_Ledger_Data!E27), ""[^0-9.]"", """")), 0)"),500.0) -> 500 | F27: =IFERROR(__xludf.DUMMYFUNCTION("IFERROR(VALUE(REGEXREPLACE(TO_TEXT(General_Ledger_Data!F27), ""[^0-9.]"", """")), 0)"),0.0) -> 0 | G27: =IF(OR(E27=0, F27=0), 0, E27*F27) -> 0 | H27: =IF(ISNUMBER(General_Ledger_Data!G27), "PASSED CLEAN", "REPAIRED") -> REPAIRED
A28: =General_Ledger_Data!A28 -> TXN-1027 | B28: =General_Ledger_Data!B28 -> 46036 | C28: =General_Ledger_Data!C28 -> 6002-CAPEX | D28: =IF(OR(ISBLANK(General_Ledger_Data!D28), General_Ledger_Data!D28="#N/A"), "VEND-UNKNOWN", General_Ledger_Data!D28) -> VEND-827 | E28: =IFERROR(__xludf.DUMMYFUNCTION("IFERROR(VALUE(REGEXREPLACE(TO_TEXT(General_Ledger_Data!E28), ""[^0-9.]"", """")), 0)"),85.0) -> 85 | F28: =IFERROR(__xludf.DUMMYFUNCTION("IFERROR(VALUE(REGEXREPLACE(TO_TEXT(General_Ledger_Data!F28), ""[^0-9.]"", """")), 0)"),180.0) -> 180 | G28: =IF(OR(E28=0, F28=0), 0, E28*F28) -> 15300 | H28: =IF(ISNUMBER(General_Ledger_Data!G28), "PASSED CLEAN", "REPAIRED") -> PASSED CLEAN
A29: =General_Ledger_Data!A29 -> TXN-1028 | B29: =General_Ledger_Data!B29 -> 46036 | C29: =General_Ledger_Data!C29 -> 6003-SUPPLY | D29: =IF(OR(ISBLANK(General_Ledger_Data!D29), General_Ledger_Data!D29="#N/A"), "VEND-UNKNOWN", General_Ledger_Data!D29) -> VEND-828 | E29: =IFERROR(__xludf.DUMMYFUNCTION("IFERROR(VALUE(REGEXREPLACE(TO_TEXT(General_Ledger_Data!E29), ""[^0-9.]"", """")), 0)"),0.0) -> 0 | F29: =IFERROR(__xludf.DUMMYFUNCTION("IFERROR(VALUE(REGEXREPLACE(TO_TEXT(General_Ledger_Data!F29), ""[^0-9.]"", """")), 0)"),85.0) -> 85 | G29: =IF(OR(E29=0, F29=0), 0, E29*F29) -> 0 | H29: =IF(ISNUMBER(General_Ledger_Data!G29), "PASSED CLEAN", "REPAIRED") -> REPAIRED
A30: =General_Ledger_Data!A30 -> TXN-1029 | B30: =General_Ledger_Data!B30 -> 46037 | C30: =General_Ledger_Data!C30 -> 6001-OPEX | D30: =IF(OR(ISBLANK(General_Ledger_Data!D30), General_Ledger_Data!D30="#N/A"), "VEND-UNKNOWN", General_Ledger_Data!D30) -> VEND-829 | E30: =IFERROR(__xludf.DUMMYFUNCTION("IFERROR(VALUE(REGEXREPLACE(TO_TEXT(General_Ledger_Data!E30), ""[^0-9.]"", """")), 0)"),135.0) -> 135 | F30: =IFERROR(__xludf.DUMMYFUNCTION("IFERROR(VALUE(REGEXREPLACE(TO_TEXT(General_Ledger_Data!F30), ""[^0-9.]"", """")), 0)"),50.0) -> 50 | G30: =IF(OR(E30=0, F30=0), 0, E30*F30) -> 6750 | H30: =IF(ISNUMBER(General_Ledger_Data!G30), "PASSED CLEAN", "REPAIRED") -> PASSED CLEAN
A31: =General_Ledger_Data!A31 -> TXN-1030 | B31: =General_Ledger_Data!B31 -> 46037 | C31: =General_Ledger_Data!C31 -> 6004-TRAVEL | D31: =IF(OR(ISBLANK(General_Ledger_Data!D31), General_Ledger_Data!D31="#N/A"), "VEND-UNKNOWN", General_Ledger_Data!D31) -> VEND-830 | E31: =IFERROR(__xludf.DUMMYFUNCTION("IFERROR(VALUE(REGEXREPLACE(TO_TEXT(General_Ledger_Data!E31), ""[^0-9.]"", """")), 0)"),70.0) -> 70 | F31: =IFERROR(__xludf.DUMMYFUNCTION("IFERROR(VALUE(REGEXREPLACE(TO_TEXT(General_Ledger_Data!F31), ""[^0-9.]"", """")), 0)"),110.0) -> 110 | G31: =IF(OR(E31=0, F31=0), 0, E31*F31) -> 7700 | H31: =IF(ISNUMBER(General_Ledger_Data!G31), "PASSED CLEAN", "REPAIRED") -> PASSED CLEAN
A32: =General_Ledger_Data!A32 -> TXN-1031 | B32: =General_Ledger_Data!B32 -> 46038 | C32: =General_Ledger_Data!C32 -> 6001-OPEX | D32: =IF(OR(ISBLANK(General_Ledger_Data!D32), General_Ledger_Data!D32="#N/A"), "VEND-UNKNOWN", General_Ledger_Data!D32) -> VEND-831 | E32: =IFERROR(__xludf.DUMMYFUNCTION("IFERROR(VALUE(REGEXREPLACE(TO_TEXT(General_Ledger_Data!E32), ""[^0-9.]"", """")), 0)"),160.0) -> 160 | F32: =IFERROR(__xludf.DUMMYFUNCTION("IFERROR(VALUE(REGEXREPLACE(TO_TEXT(General_Ledger_Data!F32), ""[^0-9.]"", """")), 0)"),42.0) -> 42 | G32: =IF(OR(E32=0, F32=0), 0, E32*F32) -> 6720 | H32: =IF(ISNUMBER(General_Ledger_Data!G32), "PASSED CLEAN", "REPAIRED") -> PASSED CLEAN
A33: =General_Ledger_Data!A33 -> TXN-1032 | B33: =General_Ledger_Data!B33 -> 46038 | C33: =General_Ledger_Data!C33 -> 6002-CAPEX | D33: =IF(OR(ISBLANK(General_Ledger_Data!D33), General_Ledger_Data!D33="#N/A"), "VEND-UNKNOWN", General_Ledger_Data!D33) -> VEND-832 | E33: =IFERROR(__xludf.DUMMYFUNCTION("IFERROR(VALUE(REGEXREPLACE(TO_TEXT(General_Ledger_Data!E33), ""[^0-9.]"", """")), 0)"),95.0) -> 95 | F33: =IFERROR(__xludf.DUMMYFUNCTION("IFERROR(VALUE(REGEXREPLACE(TO_TEXT(General_Ledger_Data!F33), ""[^0-9.]"", """")), 0)"),310.0) -> 310 | G33: =IF(OR(E33=0, F33=0), 0, E33*F33) -> 29450 | H33: =IF(ISNUMBER(General_Ledger_Data!G33), "PASSED CLEAN", "REPAIRED") -> PASSED CLEAN
A34: =General_Ledger_Data!A34 -> TXN-1033 | B34: =General_Ledger_Data!B34 -> 46039 | C34: =General_Ledger_Data!C34 -> 6003-SUPPLY | D34: =IF(OR(ISBLANK(General_Ledger_Data!D34), General_Ledger_Data!D34="#N/A"), "VEND-UNKNOWN", General_Ledger_Data!D34) -> VEND-999 | E34: =IFERROR(__xludf.DUMMYFUNCTION("IFERROR(VALUE(REGEXREPLACE(TO_TEXT(General_Ledger_Data!E34), ""[^0-9.]"", """")), 0)"),0.0) -> 0 | F34: =IFERROR(__xludf.DUMMYFUNCTION("IFERROR(VALUE(REGEXREPLACE(TO_TEXT(General_Ledger_Data!F34), ""[^0-9.]"", """")), 0)"),15.0) -> 15 | G34: =IF(OR(E34=0, F34=0), 0, E34*F34) -> 0 | H34: =IF(ISNUMBER(General_Ledger_Data!G34), "PASSED CLEAN", "REPAIRED") -> REPAIRED
A35: =General_Ledger_Data!A35 -> TXN-1034 | B35: =General_Ledger_Data!B35 -> 46039 | C35: =General_Ledger_Data!C35 -> 6001-OPEX | D35: =IF(OR(ISBLANK(General_Ledger_Data!D35), General_Ledger_Data!D35="#N/A"), "VEND-UNKNOWN", General_Ledger_Data!D35) -> VEND-834 | E35: =IFERROR(__xludf.DUMMYFUNCTION("IFERROR(VALUE(REGEXREPLACE(TO_TEXT(General_Ledger_Data!E35), ""[^0-9.]"", """")), 0)"),210.0) -> 210 | F35: =IFERROR(__xludf.DUMMYFUNCTION("IFERROR(VALUE(REGEXREPLACE(TO_TEXT(General_Ledger_Data!F35), ""[^0-9.]"", """")), 0)"),65.0) -> 65 | G35: =IF(OR(E35=0, F35=0), 0, E35*F35) -> 13650 | H35: =IF(ISNUMBER(General_Ledger_Data!G35), "PASSED CLEAN", "REPAIRED") -> PASSED CLEAN
A36: =General_Ledger_Data!A36 -> TXN-1035 | B36: =General_Ledger_Data!B36 -> 46040 | C36: =General_Ledger_Data!C36 -> 6004-TRAVEL | D36: =IF(OR(ISBLANK(General_Ledger_Data!D36), General_Ledger_Data!D36="#N/A"), "VEND-UNKNOWN", General_Ledger_Data!D36) -> VEND-835 | E36: =IFERROR(__xludf.DUMMYFUNCTION("IFERROR(VALUE(REGEXREPLACE(TO_TEXT(General_Ledger_Data!E36), ""[^0-9.]"", """")), 0)"),30.0) -> 30 | F36: =IFERROR(__xludf.DUMMYFUNCTION("IFERROR(VALUE(REGEXREPLACE(TO_TEXT(General_Ledger_Data!F36), ""[^0-9.]"", """")), 0)"),400.0) -> 400 | G36: =IF(OR(E36=0, F36=0), 0, E36*F36) -> 12000 | H36: =IF(ISNUMBER(General_Ledger_Data!G36), "PASSED CLEAN", "REPAIRED") -> PASSED CLEAN
A37: =General_Ledger_Data!A37 -> TXN-1036 | B37: =General_Ledger_Data!B37 -> 46040 | C37: =General_Ledger_Data!C37 -> 6001-OPEX | D37: =IF(OR(ISBLANK(General_Ledger_Data!D37), General_Ledger_Data!D37="#N/A"), "VEND-UNKNOWN", General_Ledger_Data!D37) -> VEND-836 | E37: =IFERROR(__xludf.DUMMYFUNCTION("IFERROR(VALUE(REGEXREPLACE(TO_TEXT(General_Ledger_Data!E37), ""[^0-9.]"", """")), 0)"),115.0) -> 115 | F37: =IFERROR(__xludf.DUMMYFUNCTION("IFERROR(VALUE(REGEXREPLACE(TO_TEXT(General_Ledger_Data!F37), ""[^0-9.]"", """")), 0)"),0.0) -> 0 | G37: =IF(OR(E37=0, F37=0), 0, E37*F37) -> 0 | H37: =IF(ISNUMBER(General_Ledger_Data!G37), "PASSED CLEAN", "REPAIRED") -> REPAIRED
A38: =General_Ledger_Data!A38 -> TXN-1037 | B38: =General_Ledger_Data!B38 -> 46041 | C38: =General_Ledger_Data!C38 -> 6002-CAPEX | D38: =IF(OR(ISBLANK(General_Ledger_Data!D38), General_Ledger_Data!D38="#N/A"), "VEND-UNKNOWN", General_Ledger_Data!D38) -> VEND-837 | E38: =IFERROR(__xludf.DUMMYFUNCTION("IFERROR(VALUE(REGEXREPLACE(TO_TEXT(General_Ledger_Data!E38), ""[^0-9.]"", """")), 0)"),350.0) -> 350 | F38: =IFERROR(__xludf.DUMMYFUNCTION("IFERROR(VALUE(REGEXREPLACE(TO_TEXT(General_Ledger_Data!F38), ""[^0-9.]"", """")), 0)"),22.0) -> 22 | G38: =IF(OR(E38=0, F38=0), 0, E38*F38) -> 7700 | H38: =IF(ISNUMBER(General_Ledger_Data!G38), "PASSED CLEAN", "REPAIRED") -> PASSED CLEAN
A39: =General_Ledger_Data!A39 -> TXN-1038 | B39: =General_Ledger_Data!B39 -> 46041 | C39: =General_Ledger_Data!C39 -> 6003-SUPPLY | D39: =IF(OR(ISBLANK(General_Ledger_Data!D39), General_Ledger_Data!D39="#N/A"), "VEND-UNKNOWN", General_Ledger_Data!D39) -> VEND-838 | E39: =IFERROR(__xludf.DUMMYFUNCTION("IFERROR(VALUE(REGEXREPLACE(TO_TEXT(General_Ledger_Data!E39), ""[^0-9.]"", """")), 0)"),0.0) -> 0 | F39: =IFERROR(__xludf.DUMMYFUNCTION("IFERROR(VALUE(REGEXREPLACE(TO_TEXT(General_Ledger_Data!F39), ""[^0-9.]"", """")), 0)"),45.0) -> 45 | G39: =IF(OR(E39=0, F39=0), 0, E39*F39) -> 0 | H39: =IF(ISNUMBER(General_Ledger_Data!G39), "PASSED CLEAN", "REPAIRED") -> REPAIRED
A40: =General_Ledger_Data!A40 -> TXN-1039 | B40: =General_Ledger_Data!B40 -> 46042 | C40: =General_Ledger_Data!C40 -> 6001-OPEX | D40: =IF(OR(ISBLANK(General_Ledger_Data!D40), General_Ledger_Data!D40="#N/A"), "VEND-UNKNOWN", General_Ledger_Data!D40) -> VEND-839 | E40: =IFERROR(__xludf.DUMMYFUNCTION("IFERROR(VALUE(REGEXREPLACE(TO_TEXT(General_Ledger_Data!E40), ""[^0-9.]"", """")), 0)"),85.0) -> 85 | F40: =IFERROR(__xludf.DUMMYFUNCTION("IFERROR(VALUE(REGEXREPLACE(TO_TEXT(General_Ledger_Data!F40), ""[^0-9.]"", """")), 0)"),125.0) -> 125 | G40: =IF(OR(E40=0, F40=0), 0, E40*F40) -> 10625 | H40: =IF(ISNUMBER(General_Ledger_Data!G40), "PASSED CLEAN", "REPAIRED") -> PASSED CLEAN
A41: =General_Ledger_Data!A41 -> TXN-1040 | B41: =General_Ledger_Data!B41 -> 46042 | C41: =General_Ledger_Data!C41 -> 6004-TRAVEL | D41: =IF(OR(ISBLANK(General_Ledger_Data!D41), General_Ledger_Data!D41="#N/A"), "VEND-UNKNOWN", General_Ledger_Data!D41) -> VEND-840 | E41: =IFERROR(__xludf.DUMMYFUNCTION("IFERROR(VALUE(REGEXREPLACE(TO_TEXT(General_Ledger_Data!E41), ""[^0-9.]"", """")), 0)"),450.0) -> 450 | F41: =IFERROR(__xludf.DUMMYFUNCTION("IFERROR(VALUE(REGEXREPLACE(TO_TEXT(General_Ledger_Data!F41), ""[^0-9.]"", """")), 0)"),8.5) -> 8.5 | G41: =IF(OR(E41=0, F41=0), 0, E41*F41) -> 3825 | H41: =IF(ISNUMBER(General_Ledger_Data!G41), "PASSED CLEAN", "REPAIRED") -> PASSED CLEAN
A42: =General_Ledger_Data!A42 -> TXN-1041 | B42: =General_Ledger_Data!B42 -> 46043 | C42: =General_Ledger_Data!C42 -> 6001-OPEX | D42: =IF(OR(ISBLANK(General_Ledger_Data!D42), General_Ledger_Data!D42="#N/A"), "VEND-UNKNOWN", General_Ledger_Data!D42) -> VEND-841 | E42: =IFERROR(__xludf.DUMMYFUNCTION("IFERROR(VALUE(REGEXREPLACE(TO_TEXT(General_Ledger_Data!E42), ""[^0-9.]"", """")), 0)"),95.0) -> 95 | F42: =IFERROR(__xludf.DUMMYFUNCTION("IFERROR(VALUE(REGEXREPLACE(TO_TEXT(General_Ledger_Data!F42), ""[^0-9.]"", """")), 0)"),75.0) -> 75 | G42: =IF(OR(E42=0, F42=0), 0, E42*F42) -> 7125 | H42: =IF(ISNUMBER(General_Ledger_Data!G42), "PASSED CLEAN", "REPAIRED") -> PASSED CLEAN
A43: =General_Ledger_Data!A43 -> TXN-1042 | B43: =General_Ledger_Data!B43 -> 46043 | C43: =General_Ledger_Data!C43 -> 6002-CAPEX | D43: =IF(OR(ISBLANK(General_Ledger_Data!D43), General_Ledger_Data!D43="#N/A"), "VEND-UNKNOWN", General_Ledger_Data!D43) -> VEND-842 | E43: =IFERROR(__xludf.DUMMYFUNCTION("IFERROR(VALUE(REGEXREPLACE(TO_TEXT(General_Ledger_Data!E43), ""[^0-9.]"", """")), 0)"),50.0) -> 50 | F43: =IFERROR(__xludf.DUMMYFUNCTION("IFERROR(VALUE(REGEXREPLACE(TO_TEXT(General_Ledger_Data!F43), ""[^0-9.]"", """")), 0)"),950.0) -> 950 | G43: =IF(OR(E43=0, F43=0), 0, E43*F43) -> 47500 | H43: =IF(ISNUMBER(General_Ledger_Data!G43), "PASSED CLEAN", "REPAIRED") -> PASSED CLEAN
A44: =General_Ledger_Data!A44 -> TXN-1043 | B44: =General_Ledger_Data!B44 -> 46044 | C44: =General_Ledger_Data!C44 -> 6003-SUPPLY | D44: =IF(OR(ISBLANK(General_Ledger_Data!D44), General_Ledger_Data!D44="#N/A"), "VEND-UNKNOWN", General_Ledger_Data!D44) -> VEND-843 | E44: =IFERROR(__xludf.DUMMYFUNCTION("IFERROR(VALUE(REGEXREPLACE(TO_TEXT(General_Ledger_Data!E44), ""[^0-9.]"", """")), 0)"),240.0) -> 240 | F44: =IFERROR(__xludf.DUMMYFUNCTION("IFERROR(VALUE(REGEXREPLACE(TO_TEXT(General_Ledger_Data!F44), ""[^0-9.]"", """")), 0)"),25.0) -> 25 | G44: =IF(OR(E44=0, F44=0), 0, E44*F44) -> 6000 | H44: =IF(ISNUMBER(General_Ledger_Data!G44), "PASSED CLEAN", "REPAIRED") -> PASSED CLEAN
A45: =General_Ledger_Data!A45 -> TXN-1044 | B45: =General_Ledger_Data!B45 -> 46044 | C45: =General_Ledger_Data!C45 -> 6001-OPEX | D45: =IF(OR(ISBLANK(General_Ledger_Data!D45), General_Ledger_Data!D45="#N/A"), "VEND-UNKNOWN", General_Ledger_Data!D45) -> VEND-844 | E45: =IFERROR(__xludf.DUMMYFUNCTION("IFERROR(VALUE(REGEXREPLACE(TO_TEXT(General_Ledger_Data!E45), ""[^0-9.]"", """")), 0)"),0.0) -> 0 | F45: =IFERROR(__xludf.DUMMYFUNCTION("IFERROR(VALUE(REGEXREPLACE(TO_TEXT(General_Ledger_Data!F45), ""[^0-9.]"", """")), 0)"),60.0) -> 60 | G45: =IF(OR(E45=0, F45=0), 0, E45*F45) -> 0 | H45: =IF(ISNUMBER(General_Ledger_Data!G45), "PASSED CLEAN", "REPAIRED") -> REPAIRED
A46: =General_Ledger_Data!A46 -> TXN-1045 | B46: =General_Ledger_Data!B46 -> 46045 | C46: =General_Ledger_Data!C46 -> 6004-TRAVEL | D46: =IF(OR(ISBLANK(General_Ledger_Data!D46), General_Ledger_Data!D46="#N/A"), "VEND-UNKNOWN", General_Ledger_Data!D46) -> VEND-845 | E46: =IFERROR(__xludf.DUMMYFUNCTION("IFERROR(VALUE(REGEXREPLACE(TO_TEXT(General_Ledger_Data!E46), ""[^0-9.]"", """")), 0)"),18.0) -> 18 | F46: =IFERROR(__xludf.DUMMYFUNCTION("IFERROR(VALUE(REGEXREPLACE(TO_TEXT(General_Ledger_Data!F46), ""[^0-9.]"", """")), 0)"),550.0) -> 550 | G46: =IF(OR(E46=0, F46=0), 0, E46*F46) -> 9900 | H46: =IF(ISNUMBER(General_Ledger_Data!G46), "PASSED CLEAN", "REPAIRED") -> PASSED CLEAN
A47: =General_Ledger_Data!A47 -> TXN-1046 | B47: =General_Ledger_Data!B47 -> 46045 | C47: =General_Ledger_Data!C47 -> 6001-OPEX | D47: =IF(OR(ISBLANK(General_Ledger_Data!D47), General_Ledger_Data!D47="#N/A"), "VEND-UNKNOWN", General_Ledger_Data!D47) -> VEND-999 | E47: =IFERROR(__xludf.DUMMYFUNCTION("IFERROR(VALUE(REGEXREPLACE(TO_TEXT(General_Ledger_Data!E47), ""[^0-9.]"", """")), 0)"),0.0) -> 0 | F47: =IFERROR(__xludf.DUMMYFUNCTION("IFERROR(VALUE(REGEXREPLACE(TO_TEXT(General_Ledger_Data!F47), ""[^0-9.]"", """")), 0)"),0.0) -> 0 | G47: =IF(OR(E47=0, F47=0), 0, E47*F47) -> 0 | H47: =IF(ISNUMBER(General_Ledger_Data!G47), "PASSED CLEAN", "REPAIRED") -> REPAIRED
A48: =General_Ledger_Data!A48 -> TXN-1047 | B48: =General_Ledger_Data!B48 -> 46046 | C48: =General_Ledger_Data!C48 -> 6002-CAPEX | D48: =IF(OR(ISBLANK(General_Ledger_Data!D48), General_Ledger_Data!D48="#N/A"), "VEND-UNKNOWN", General_Ledger_Data!D48) -> VEND-847 | E48: =IFERROR(__xludf.DUMMYFUNCTION("IFERROR(VALUE(REGEXREPLACE(TO_TEXT(General_Ledger_Data!E48), ""[^0-9.]"", """")), 0)"),105.0) -> 105 | F48: =IFERROR(__xludf.DUMMYFUNCTION("IFERROR(VALUE(REGEXREPLACE(TO_TEXT(General_Ledger_Data!F48), ""[^0-9.]"", """")), 0)"),140.0) -> 140 | G48: =IF(OR(E48=0, F48=0), 0, E48*F48) -> 14700 | H48: =IF(ISNUMBER(General_Ledger_Data!G48), "PASSED CLEAN", "REPAIRED") -> PASSED CLEAN
A49: =General_Ledger_Data!A49 -> TXN-1048 | B49: =General_Ledger_Data!B49 -> 46046 | C49: =General_Ledger_Data!C49 -> 6003-SUPPLY | D49: =IF(OR(ISBLANK(General_Ledger_Data!D49), General_Ledger_Data!D49="#N/A"), "VEND-UNKNOWN", General_Ledger_Data!D49) -> VEND-848 | E49: =IFERROR(__xludf.DUMMYFUNCTION("IFERROR(VALUE(REGEXREPLACE(TO_TEXT(General_Ledger_Data!E49), ""[^0-9.]"", """")), 0)"),0.0) -> 0 | F49: =IFERROR(__xludf.DUMMYFUNCTION("IFERROR(VALUE(REGEXREPLACE(TO_TEXT(General_Ledger_Data!F49), ""[^0-9.]"", """")), 0)"),130.0) -> 130 | G49: =IF(OR(E49=0, F49=0), 0, E49*F49) -> 0 | H49: =IF(ISNUMBER(General_Ledger_Data!G49), "PASSED CLEAN", "REPAIRED") -> REPAIRED
A50: =General_Ledger_Data!A50 -> TXN-1049 | B50: =General_Ledger_Data!B50 -> 46047 | C50: =General_Ledger_Data!C50 -> 6001-OPEX | D50: =IF(OR(ISBLANK(General_Ledger_Data!D50), General_Ledger_Data!D50="#N/A"), "VEND-UNKNOWN", General_Ledger_Data!D50) -> VEND-849 | E50: =IFERROR(__xludf.DUMMYFUNCTION("IFERROR(VALUE(REGEXREPLACE(TO_TEXT(General_Ledger_Data!E50), ""[^0-9.]"", """")), 0)"),125.0) -> 125 | F50: =IFERROR(__xludf.DUMMYFUNCTION("IFERROR(VALUE(REGEXREPLACE(TO_TEXT(General_Ledger_Data!F50), ""[^0-9.]"", """")), 0)"),80.0) -> 80 | G50: =IF(OR(E50=0, F50=0), 0, E50*F50) -> 10000 | H50: =IF(ISNUMBER(General_Ledger_Data!G50), "PASSED CLEAN", "REPAIRED") -> PASSED CLEAN
A51: =General_Ledger_Data!A51 -> TXN-1050 | B51: =General_Ledger_Data!B51 -> 46047 | C51: =General_Ledger_Data!C51 -> 6004-TRAVEL | D51: =IF(OR(ISBLANK(General_Ledger_Data!D51), General_Ledger_Data!D51="#N/A"), "VEND-UNKNOWN", General_Ledger_Data!D51) -> VEND-850 | E51: =IFERROR(__xludf.DUMMYFUNCTION("IFERROR(VALUE(REGEXREPLACE(TO_TEXT(General_Ledger_Data!E51), ""[^0-9.]"", """")), 0)"),320.0) -> 320 | F51: =IFERROR(__xludf.DUMMYFUNCTION("IFERROR(VALUE(REGEXREPLACE(TO_TEXT(General_Ledger_Data!F51), ""[^0-9.]"", """")), 0)"),18.25) -> 18.25 | G51: =IF(OR(E51=0, F51=0), 0, E51*F51) -> 5840 | H51: =IF(ISNUMBER(General_Ledger_Data!G51), "PASSED CLEAN", "REPAIRED") -> PASSED CLEAN
A52: =General_Ledger_Data!A52 -> TXN-1051 | B52: =General_Ledger_Data!B52 -> 46048 | C52: =General_Ledger_Data!C52 -> 6001-OPEX | D52: =IF(OR(ISBLANK(General_Ledger_Data!D52), General_Ledger_Data!D52="#N/A"), "VEND-UNKNOWN", General_Ledger_Data!D52) -> VEND-851 | E52: =IFERROR(__xludf.DUMMYFUNCTION("IFERROR(VALUE(REGEXREPLACE(TO_TEXT(General_Ledger_Data!E52), ""[^0-9.]"", """")), 0)"),140.0) -> 140 | F52: =IFERROR(__xludf.DUMMYFUNCTION("IFERROR(VALUE(REGEXREPLACE(TO_TEXT(General_Ledger_Data!F52), ""[^0-9.]"", """")), 0)"),55.0) -> 55 | G52: =IF(OR(E52=0, F52=0), 0, E52*F52) -> 7700 | H52: =IF(ISNUMBER(General_Ledger_Data!G52), "PASSED CLEAN", "REPAIRED") -> PASSED CLEAN
A53: =General_Ledger_Data!A53 -> TXN-1052 | B53: =General_Ledger_Data!B53 -> 46048 | C53: =General_Ledger_Data!C53 -> 6002-CAPEX | D53: =IF(OR(ISBLANK(General_Ledger_Data!D53), General_Ledger_Data!D53="#N/A"), "VEND-UNKNOWN", General_Ledger_Data!D53) -> VEND-852 | E53: =IFERROR(__xludf.DUMMYFUNCTION("IFERROR(VALUE(REGEXREPLACE(TO_TEXT(General_Ledger_Data!E53), ""[^0-9.]"", """")), 0)"),75.0) -> 75 | F53: =IFERROR(__xludf.DUMMYFUNCTION("IFERROR(VALUE(REGEXREPLACE(TO_TEXT(General_Ledger_Data!F53), ""[^0-9.]"", """")), 0)"),420.0) -> 420 | G53: =IF(OR(E53=0, F53=0), 0, E53*F53) -> 31500 | H53: =IF(ISNUMBER(General_Ledger_Data!G53), "PASSED CLEAN", "REPAIRED") -> PASSED CLEAN
A54: =General_Ledger_Data!A54 -> TXN-1053 | B54: =General_Ledger_Data!B54 -> 46049 | C54: =General_Ledger_Data!C54 -> 6003-SUPPLY | D54: =IF(OR(ISBLANK(General_Ledger_Data!D54), General_Ledger_Data!D54="#N/A"), "VEND-UNKNOWN", General_Ledger_Data!D54) -> VEND-853 | E54: =IFERROR(__xludf.DUMMYFUNCTION("IFERROR(VALUE(REGEXREPLACE(TO_TEXT(General_Ledger_Data!E54), ""[^0-9.]"", """")), 0)"),190.0) -> 190 | F54: =IFERROR(__xludf.DUMMYFUNCTION("IFERROR(VALUE(REGEXREPLACE(TO_TEXT(General_Ledger_Data!F54), ""[^0-9.]"", """")), 0)"),30.0) -> 30 | G54: =IF(OR(E54=0, F54=0), 0, E54*F54) -> 5700 | H54: =IF(ISNUMBER(General_Ledger_Data!G54), "PASSED CLEAN", "REPAIRED") -> PASSED CLEAN
A55: =General_Ledger_Data!A55 -> TXN-1054 | B55: =General_Ledger_Data!B55 -> 46049 | C55: =General_Ledger_Data!C55 -> 6001-OPEX | D55: =IF(OR(ISBLANK(General_Ledger_Data!D55), General_Ledger_Data!D55="#N/A"), "VEND-UNKNOWN", General_Ledger_Data!D55) -> VEND-854 | E55: =IFERROR(__xludf.DUMMYFUNCTION("IFERROR(VALUE(REGEXREPLACE(TO_TEXT(General_Ledger_Data!E55), ""[^0-9.]"", """")), 0)"),0.0) -> 0 | F55: =IFERROR(__xludf.DUMMYFUNCTION("IFERROR(VALUE(REGEXREPLACE(TO_TEXT(General_Ledger_Data!F55), ""[^0-9.]"", """")), 0)"),85.0) -> 85 | G55: =IF(OR(E55=0, F55=0), 0, E55*F55) -> 0 | H55: =IF(ISNUMBER(General_Ledger_Data!G55), "PASSED CLEAN", "REPAIRED") -> REPAIRED
A56: =General_Ledger_Data!A56 -> TXN-1055 | B56: =General_Ledger_Data!B56 -> 46050 | C56: =General_Ledger_Data!C56 -> 6004-TRAVEL | D56: =IF(OR(ISBLANK(General_Ledger_Data!D56), General_Ledger_Data!D56="#N/A"), "VEND-UNKNOWN", General_Ledger_Data!D56) -> VEND-855 | E56: =IFERROR(__xludf.DUMMYFUNCTION("IFERROR(VALUE(REGEXREPLACE(TO_TEXT(General_Ledger_Data!E56), ""[^0-9.]"", """")), 0)"),55.0) -> 55 | F56: =IFERROR(__xludf.DUMMYFUNCTION("IFERROR(VALUE(REGEXREPLACE(TO_TEXT(General_Ledger_Data!F56), ""[^0-9.]"", """")), 0)"),290.0) -> 290 | G56: =IF(OR(E56=0, F56=0), 0, E56*F56) -> 15950 | H56: =IF(ISNUMBER(General_Ledger_Data!G56), "PASSED CLEAN", "REPAIRED") -> PASSED CLEAN
A57: =General_Ledger_Data!A57 -> TXN-1056 | B57: =General_Ledger_Data!B57 -> 46050 | C57: =General_Ledger_Data!C57 -> 6001-OPEX | D57: =IF(OR(ISBLANK(General_Ledger_Data!D57), General_Ledger_Data!D57="#N/A"), "VEND-UNKNOWN", General_Ledger_Data!D57) -> VEND-999 | E57: =IFERROR(__xludf.DUMMYFUNCTION("IFERROR(VALUE(REGEXREPLACE(TO_TEXT(General_Ledger_Data!E57), ""[^0-9.]"", """")), 0)"),400.0) -> 400 | F57: =IFERROR(__xludf.DUMMYFUNCTION("IFERROR(VALUE(REGEXREPLACE(TO_TEXT(General_Ledger_Data!F57), ""[^0-9.]"", """")), 0)"),0.0) -> 0 | G57: =IF(OR(E57=0, F57=0), 0, E57*F57) -> 0 | H57: =IF(ISNUMBER(General_Ledger_Data!G57), "PASSED CLEAN", "REPAIRED") -> REPAIRED
A58: =General_Ledger_Data!A58 -> TXN-1057 | B58: =General_Ledger_Data!B58 -> 46051 | C58: =General_Ledger_Data!C58 -> 6002-CAPEX | D58: =IF(OR(ISBLANK(General_Ledger_Data!D58), General_Ledger_Data!D58="#N/A"), "VEND-UNKNOWN", General_Ledger_Data!D58) -> VEND-857 | E58: =IFERROR(__xludf.DUMMYFUNCTION("IFERROR(VALUE(REGEXREPLACE(TO_TEXT(General_Ledger_Data!E58), ""[^0-9.]"", """")), 0)"),110.0) -> 110 | F58: =IFERROR(__xludf.DUMMYFUNCTION("IFERROR(VALUE(REGEXREPLACE(TO_TEXT(General_Ledger_Data!F58), ""[^0-9.]"", """")), 0)"),165.0) -> 165 | G58: =IF(OR(E58=0, F58=0), 0, E58*F58) -> 18150 | H58: =IF(ISNUMBER(General_Ledger_Data!G58), "PASSED CLEAN", "REPAIRED") -> PASSED CLEAN
A59: =General_Ledger_Data!A59 -> TXN-1058 | B59: =General_Ledger_Data!B59 -> 46051 | C59: =General_Ledger_Data!C59 -> 6003-SUPPLY | D59: =IF(OR(ISBLANK(General_Ledger_Data!D59), General_Ledger_Data!D59="#N/A"), "VEND-UNKNOWN", General_Ledger_Data!D59) -> VEND-858 | E59: =IFERROR(__xludf.DUMMYFUNCTION("IFERROR(VALUE(REGEXREPLACE(TO_TEXT(General_Ledger_Data!E59), ""[^0-9.]"", """")), 0)"),0.0) -> 0 | F59: =IFERROR(__xludf.DUMMYFUNCTION("IFERROR(VALUE(REGEXREPLACE(TO_TEXT(General_Ledger_Data!F59), ""[^0-9.]"", """")), 0)"),95.0) -> 95 | G59: =IF(OR(E59=0, F59=0), 0, E59*F59) -> 0 | H59: =IF(ISNUMBER(General_Ledger_Data!G59), "PASSED CLEAN", "REPAIRED") -> REPAIRED
A60: =General_Ledger_Data!A60 -> TXN-1059 | B60: =General_Ledger_Data!B60 -> 46052 | C60: =General_Ledger_Data!C60 -> 6001-OPEX | D60: =IF(OR(ISBLANK(General_Ledger_Data!D60), General_Ledger_Data!D60="#N/A"), "VEND-UNKNOWN", General_Ledger_Data!D60) -> VEND-859 | E60: =IFERROR(__xludf.DUMMYFUNCTION("IFERROR(VALUE(REGEXREPLACE(TO_TEXT(General_Ledger_Data!E60), ""[^0-9.]"", """")), 0)"),165.0) -> 165 | F60: =IFERROR(__xludf.DUMMYFUNCTION("IFERROR(VALUE(REGEXREPLACE(TO_TEXT(General_Ledger_Data!F60), ""[^0-9.]"", """")), 0)"),48.0) -> 48 | G60: =IF(OR(E60=0, F60=0), 0, E60*F60) -> 7920 | H60: =IF(ISNUMBER(General_Ledger_Data!G60), "PASSED CLEAN", "REPAIRED") -> PASSED CLEAN
A61: =General_Ledger_Data!A61 -> TXN-1060 | B61: =General_Ledger_Data!B61 -> 46052 | C61: =General_Ledger_Data!C61 -> 6004-TRAVEL | D61: =IF(OR(ISBLANK(General_Ledger_Data!D61), General_Ledger_Data!D61="#N/A"), "VEND-UNKNOWN", General_Ledger_Data!D61) -> VEND-860 | E61: =IFERROR(__xludf.DUMMYFUNCTION("IFERROR(VALUE(REGEXREPLACE(TO_TEXT(General_Ledger_Data!E61), ""[^0-9.]"", """")), 0)"),280.0) -> 280 | F61: =IFERROR(__xludf.DUMMYFUNCTION("IFERROR(VALUE(REGEXREPLACE(TO_TEXT(General_Ledger_Data!F61), ""[^0-9.]"", """")), 0)"),14.5) -> 14.5 | G61: =IF(OR(E61=0, F61=0), 0, E61*F61) -> 4060 | H61: =IF(ISNUMBER(General_Ledger_Data!G61), "PASSED CLEAN", "REPAIRED") -> PASSED CLEAN
A62: =General_Ledger_Data!A62 -> TXN-1061 | B62: =General_Ledger_Data!B62 -> 46053 | C62: =General_Ledger_Data!C62 -> 6001-OPEX | D62: =IF(OR(ISBLANK(General_Ledger_Data!D62), General_Ledger_Data!D62="#N/A"), "VEND-UNKNOWN", General_Ledger_Data!D62) -> VEND-861 | E62: =IFERROR(__xludf.DUMMYFUNCTION("IFERROR(VALUE(REGEXREPLACE(TO_TEXT(General_Ledger_Data!E62), ""[^0-9.]"", """")), 0)"),115.0) -> 115 | F62: =IFERROR(__xludf.DUMMYFUNCTION("IFERROR(VALUE(REGEXREPLACE(TO_TEXT(General_Ledger_Data!F62), ""[^0-9.]"", """")), 0)"),62.0) -> 62 | G62: =IF(OR(E62=0, F62=0), 0, E62*F62) -> 7130 | H62: =IF(ISNUMBER(General_Ledger_Data!G62), "PASSED CLEAN", "REPAIRED") -> PASSED CLEAN
A63: =General_Ledger_Data!A63 -> TXN-1062 | B63: =General_Ledger_Data!B63 -> 46053 | C63: =General_Ledger_Data!C63 -> 6002-CAPEX | D63: =IF(OR(ISBLANK(General_Ledger_Data!D63), General_Ledger_Data!D63="#N/A"), "VEND-UNKNOWN", General_Ledger_Data!D63) -> VEND-862 | E63: =IFERROR(__xludf.DUMMYFUNCTION("IFERROR(VALUE(REGEXREPLACE(TO_TEXT(General_Ledger_Data!E63), ""[^0-9.]"", """")), 0)"),60.0) -> 60 | F63: =IFERROR(__xludf.DUMMYFUNCTION("IFERROR(VALUE(REGEXREPLACE(TO_TEXT(General_Ledger_Data!F63), ""[^0-9.]"", """")), 0)"),850.0) -> 850 | G63: =IF(OR(E63=0, F63=0), 0, E63*F63) -> 51000 | H63: =IF(ISNUMBER(General_Ledger_Data!G63), "PASSED CLEAN", "REPAIRED") -> PASSED CLEAN
A64: =General_Ledger_Data!A64 -> TXN-1063 | B64: =General_Ledger_Data!B64 -> 46054 | C64: =General_Ledger_Data!C64 -> 6003-SUPPLY | D64: =IF(OR(ISBLANK(General_Ledger_Data!D64), General_Ledger_Data!D64="#N/A"), "VEND-UNKNOWN", General_Ledger_Data!D64) -> VEND-999 | E64: =IFERROR(__xludf.DUMMYFUNCTION("IFERROR(VALUE(REGEXREPLACE(TO_TEXT(General_Ledger_Data!E64), ""[^0-9.]"", """")), 0)"),0.0) -> 0 | F64: =IFERROR(__xludf.DUMMYFUNCTION("IFERROR(VALUE(REGEXREPLACE(TO_TEXT(General_Ledger_Data!F64), ""[^0-9.]"", """")), 0)"),22.0) -> 22 | G64: =IF(OR(E64=0, F64=0), 0, E64*F64) -> 0 | H64: =IF(ISNUMBER(General_Ledger_Data!G64), "PASSED CLEAN", "REPAIRED") -> REPAIRED
A65: =General_Ledger_Data!A65 -> TXN-1064 | B65: =General_Ledger_Data!B65 -> 46054 | C65: =General_Ledger_Data!C65 -> 6001-OPEX | D65: =IF(OR(ISBLANK(General_Ledger_Data!D65), General_Ledger_Data!D65="#N/A"), "VEND-UNKNOWN", General_Ledger_Data!D65) -> VEND-864 | E65: =IFERROR(__xludf.DUMMYFUNCTION("IFERROR(VALUE(REGEXREPLACE(TO_TEXT(General_Ledger_Data!E65), ""[^0-9.]"", """")), 0)"),175.0) -> 175 | F65: =IFERROR(__xludf.DUMMYFUNCTION("IFERROR(VALUE(REGEXREPLACE(TO_TEXT(General_Ledger_Data!F65), ""[^0-9.]"", """")), 0)"),40.0) -> 40 | G65: =IF(OR(E65=0, F65=0), 0, E65*F65) -> 7000 | H65: =IF(ISNUMBER(General_Ledger_Data!G65), "PASSED CLEAN", "REPAIRED") -> PASSED CLEAN
A66: =General_Ledger_Data!A66 -> TXN-1065 | B66: =General_Ledger_Data!B66 -> 46055 | C66: =General_Ledger_Data!C66 -> 6004-TRAVEL | D66: =IF(OR(ISBLANK(General_Ledger_Data!D66), General_Ledger_Data!D66="#N/A"), "VEND-UNKNOWN", General_Ledger_Data!D66) -> VEND-865 | E66: =IFERROR(__xludf.DUMMYFUNCTION("IFERROR(VALUE(REGEXREPLACE(TO_TEXT(General_Ledger_Data!E66), ""[^0-9.]"", """")), 0)"),25.0) -> 25 | F66: =IFERROR(__xludf.DUMMYFUNCTION("IFERROR(VALUE(REGEXREPLACE(TO_TEXT(General_Ledger_Data!F66), ""[^0-9.]"", """")), 0)"),380.0) -> 380 | G66: =IF(OR(E66=0, F66=0), 0, E66*F66) -> 9500 | H66: =IF(ISNUMBER(General_Ledger_Data!G66), "PASSED CLEAN", "REPAIRED") -> PASSED CLEAN
A67: =General_Ledger_Data!A67 -> TXN-1066 | B67: =General_Ledger_Data!B67 -> 46055 | C67: =General_Ledger_Data!C67 -> 6001-OPEX | D67: =IF(OR(ISBLANK(General_Ledger_Data!D67), General_Ledger_Data!D67="#N/A"), "VEND-UNKNOWN", General_Ledger_Data!D67) -> VEND-866 | E67: =IFERROR(__xludf.DUMMYFUNCTION("IFERROR(VALUE(REGEXREPLACE(TO_TEXT(General_Ledger_Data!E67), ""[^0-9.]"", """")), 0)"),80.0) -> 80 | F67: =IFERROR(__xludf.DUMMYFUNCTION("IFERROR(VALUE(REGEXREPLACE(TO_TEXT(General_Ledger_Data!F67), ""[^0-9.]"", """")), 0)"),0.0) -> 0 | G67: =IF(OR(E67=0, F67=0), 0, E67*F67) -> 0 | H67: =IF(ISNUMBER(General_Ledger_Data!G67), "PASSED CLEAN", "REPAIRED") -> REPAIRED
A68: =General_Ledger_Data!A68 -> TXN-1067 | B68: =General_Ledger_Data!B68 -> 46056 | C68: =General_Ledger_Data!C68 -> 6002-CAPEX | D68: =IF(OR(ISBLANK(General_Ledger_Data!D68), General_Ledger_Data!D68="#N/A"), "VEND-UNKNOWN", General_Ledger_Data!D68) -> VEND-867 | E68: =IFERROR(__xludf.DUMMYFUNCTION("IFERROR(VALUE(REGEXREPLACE(TO_TEXT(General_Ledger_Data!E68), ""[^0-9.]"", """")), 0)"),290.0) -> 290 | F68: =IFERROR(__xludf.DUMMYFUNCTION("IFERROR(VALUE(REGEXREPLACE(TO_TEXT(General_Ledger_Data!F68), ""[^0-9.]"", """")), 0)"),24.0) -> 24 | G68: =IF(OR(E68=0, F68=0), 0, E68*F68) -> 6960 | H68: =IF(ISNUMBER(General_Ledger_Data!G68), "PASSED CLEAN", "REPAIRED") -> PASSED CLEAN
A69: =General_Ledger_Data!A69 -> TXN-1068 | B69: =General_Ledger_Data!B69 -> 46056 | C69: =General_Ledger_Data!C69 -> 6003-SUPPLY | D69: =IF(OR(ISBLANK(General_Ledger_Data!D69), General_Ledger_Data!D69="#N/A"), "VEND-UNKNOWN", General_Ledger_Data!D69) -> VEND-868 | E69: =IFERROR(__xludf.DUMMYFUNCTION("IFERROR(VALUE(REGEXREPLACE(TO_TEXT(General_Ledger_Data!E69), ""[^0-9.]"", """")), 0)"),0.0) -> 0 | F69: =IFERROR(__xludf.DUMMYFUNCTION("IFERROR(VALUE(REGEXREPLACE(TO_TEXT(General_Ledger_Data!F69), ""[^0-9.]"", """")), 0)"),60.0) -> 60 | G69: =IF(OR(E69=0, F69=0), 0, E69*F69) -> 0 | H69: =IF(ISNUMBER(General_Ledger_Data!G69), "PASSED CLEAN", "REPAIRED") -> REPAIRED
A70: =General_Ledger_Data!A70 -> TXN-1069 | B70: =General_Ledger_Data!B70 -> 46057 | C70: =General_Ledger_Data!C70 -> 6001-OPEX | D70: =IF(OR(ISBLANK(General_Ledger_Data!D70), General_Ledger_Data!D70="#N/A"), "VEND-UNKNOWN", General_Ledger_Data!D70) -> VEND-999 | E70: =IFERROR(__xludf.DUMMYFUNCTION("IFERROR(VALUE(REGEXREPLACE(TO_TEXT(General_Ledger_Data!E70), ""[^0-9.]"", """")), 0)"),100.0) -> 100 | F70: =IFERROR(__xludf.DUMMYFUNCTION("IFERROR(VALUE(REGEXREPLACE(TO_TEXT(General_Ledger_Data!F70), ""[^0-9.]"", """")), 0)"),0.0) -> 0 | G70: =IF(OR(E70=0, F70=0), 0, E70*F70) -> 0 | H70: =IF(ISNUMBER(General_Ledger_Data!G70), "PASSED CLEAN", "REPAIRED") -> REPAIRED
A71: =General_Ledger_Data!A71 -> TXN-1070 | B71: =General_Ledger_Data!B71 -> 46057 | C71: =General_Ledger_Data!C71 -> 6004-TRAVEL | D71: =IF(OR(ISBLANK(General_Ledger_Data!D71), General_Ledger_Data!D71="#N/A"), "VEND-UNKNOWN", General_Ledger_Data!D71) -> VEND-870 | E71: =IFERROR(__xludf.DUMMYFUNCTION("IFERROR(VALUE(REGEXREPLACE(TO_TEXT(General_Ledger_Data!E71), ""[^0-9.]"", """")), 0)"),350.0) -> 350 | F71: =IFERROR(__xludf.DUMMYFUNCTION("IFERROR(VALUE(REGEXREPLACE(TO_TEXT(General_Ledger_Data!F71), ""[^0-9.]"", """")), 0)"),16.5) -> 16.5 | G71: =IF(OR(E71=0, F71=0), 0, E71*F71) -> 5775 | H71: =IF(ISNUMBER(General_Ledger_Data!G71), "PASSED CLEAN", "REPAIRED") -> PASSED CLEAN
A72: =General_Ledger_Data!A72 -> TXN-1071 | B72: =General_Ledger_Data!B72 -> 46058 | C72: =General_Ledger_Data!C72 -> 6001-OPEX | D72: =IF(OR(ISBLANK(General_Ledger_Data!D72), General_Ledger_Data!D72="#N/A"), "VEND-UNKNOWN", General_Ledger_Data!D72) -> VEND-871 | E72: =IFERROR(__xludf.DUMMYFUNCTION("IFERROR(VALUE(REGEXREPLACE(TO_TEXT(General_Ledger_Data!E72), ""[^0-9.]"", """")), 0)"),130.0) -> 130 | F72: =IFERROR(__xludf.DUMMYFUNCTION("IFERROR(VALUE(REGEXREPLACE(TO_TEXT(General_Ledger_Data!F72), ""[^0-9.]"", """")), 0)"),52.0) -> 52 | G72: =IF(OR(E72=0, F72=0), 0, E72*F72) -> 6760 | H72: =IF(ISNUMBER(General_Ledger_Data!G72), "PASSED CLEAN", "REPAIRED") -> PASSED CLEAN
A73: =General_Ledger_Data!A73 -> TXN-1072 | B73: =General_Ledger_Data!B73 -> 46058 | C73: =General_Ledger_Data!C73 -> 6002-CAPEX | D73: =IF(OR(ISBLANK(General_Ledger_Data!D73), General_Ledger_Data!D73="#N/A"), "VEND-UNKNOWN", General_Ledger_Data!D73) -> VEND-872 | E73: =IFERROR(__xludf.DUMMYFUNCTION("IFERROR(VALUE(REGEXREPLACE(TO_TEXT(General_Ledger_Data!E73), ""[^0-9.]"", """")), 0)"),45.0) -> 45 | F73: =IFERROR(__xludf.DUMMYFUNCTION("IFERROR(VALUE(REGEXREPLACE(TO_TEXT(General_Ledger_Data!F73), ""[^0-9.]"", """")), 0)"),520.0) -> 520 | G73: =IF(OR(E73=0, F73=0), 0, E73*F73) -> 23400 | H73: =IF(ISNUMBER(General_Ledger_Data!G73), "PASSED CLEAN", "REPAIRED") -> PASSED CLEAN
A74: =General_Ledger_Data!A74 -> TXN-1073 | B74: =General_Ledger_Data!B74 -> 46059 | C74: =General_Ledger_Data!C74 -> 6003-SUPPLY | D74: =IF(OR(ISBLANK(General_Ledger_Data!D74), General_Ledger_Data!D74="#N/A"), "VEND-UNKNOWN", General_Ledger_Data!D74) -> VEND-873 | E74: =IFERROR(__xludf.DUMMYFUNCTION("IFERROR(VALUE(REGEXREPLACE(TO_TEXT(General_Ledger_Data!E74), ""[^0-9.]"", """")), 0)"),210.0) -> 210 | F74: =IFERROR(__xludf.DUMMYFUNCTION("IFERROR(VALUE(REGEXREPLACE(TO_TEXT(General_Ledger_Data!F74), ""[^0-9.]"", """")), 0)"),28.0) -> 28 | G74: =IF(OR(E74=0, F74=0), 0, E74*F74) -> 5880 | H74: =IF(ISNUMBER(General_Ledger_Data!G74), "PASSED CLEAN", "REPAIRED") -> PASSED CLEAN
A75: =General_Ledger_Data!A75 -> TXN-1074 | B75: =General_Ledger_Data!B75 -> 46059 | C75: =General_Ledger_Data!C75 -> 6001-OPEX | D75: =IF(OR(ISBLANK(General_Ledger_Data!D75), General_Ledger_Data!D75="#N/A"), "VEND-UNKNOWN", General_Ledger_Data!D75) -> VEND-874 | E75: =IFERROR(__xludf.DUMMYFUNCTION("IFERROR(VALUE(REGEXREPLACE(TO_TEXT(General_Ledger_Data!E75), ""[^0-9.]"", """")), 0)"),0.0) -> 0 | F75: =IFERROR(__xludf.DUMMYFUNCTION("IFERROR(VALUE(REGEXREPLACE(TO_TEXT(General_Ledger_Data!F75), ""[^0-9.]"", """")), 0)"),70.0) -> 70 | G75: =IF(OR(E75=0, F75=0), 0, E75*F75) -> 0 | H75: =IF(ISNUMBER(General_Ledger_Data!G75), "PASSED CLEAN", "REPAIRED") -> REPAIRED
A76: =General_Ledger_Data!A76 -> TXN-1075 | B76: =General_Ledger_Data!B76 -> 46060 | C76: =General_Ledger_Data!C76 -> 6004-TRAVEL | D76: =IF(OR(ISBLANK(General_Ledger_Data!D76), General_Ledger_Data!D76="#N/A"), "VEND-UNKNOWN", General_Ledger_Data!D76) -> VEND-875 | E76: =IFERROR(__xludf.DUMMYFUNCTION("IFERROR(VALUE(REGEXREPLACE(TO_TEXT(General_Ledger_Data!E76), ""[^0-9.]"", """")), 0)"),35.0) -> 35 | F76: =IFERROR(__xludf.DUMMYFUNCTION("IFERROR(VALUE(REGEXREPLACE(TO_TEXT(General_Ledger_Data!F76), ""[^0-9.]"", """")), 0)"),310.0) -> 310 | G76: =IF(OR(E76=0, F76=0), 0, E76*F76) -> 10850 | H76: =IF(ISNUMBER(General_Ledger_Data!G76), "PASSED CLEAN", "REPAIRED") -> PASSED CLEAN
A77: =General_Ledger_Data!A77 -> TXN-1076 | B77: =General_Ledger_Data!B77 -> 46060 | C77: =General_Ledger_Data!C77 -> 6001-OPEX | D77: =IF(OR(ISBLANK(General_Ledger_Data!D77), General_Ledger_Data!D77="#N/A"), "VEND-UNKNOWN", General_Ledger_Data!D77) -> VEND-999 | E77: =IFERROR(__xludf.DUMMYFUNCTION("IFERROR(VALUE(REGEXREPLACE(TO_TEXT(General_Ledger_Data!E77), ""[^0-9.]"", """")), 0)"),300.0) -> 300 | F77: =IFERROR(__xludf.DUMMYFUNCTION("IFERROR(VALUE(REGEXREPLACE(TO_TEXT(General_Ledger_Data!F77), ""[^0-9.]"", """")), 0)"),0.0) -> 0 | G77: =IF(OR(E77=0, F77=0), 0, E77*F77) -> 0 | H77: =IF(ISNUMBER(General_Ledger_Data!G77), "PASSED CLEAN", "REPAIRED") -> REPAIRED
A78: =General_Ledger_Data!A78 -> TXN-1077 | B78: =General_Ledger_Data!B78 -> 46061 | C78: =General_Ledger_Data!C78 -> 6002-CAPEX | D78: =IF(OR(ISBLANK(General_Ledger_Data!D78), General_Ledger_Data!D78="#N/A"), "VEND-UNKNOWN", General_Ledger_Data!D78) -> VEND-877 | E78: =IFERROR(__xludf.DUMMYFUNCTION("IFERROR(VALUE(REGEXREPLACE(TO_TEXT(General_Ledger_Data!E78), ""[^0-9.]"", """")), 0)"),95.0) -> 95 | F78: =IFERROR(__xludf.DUMMYFUNCTION("IFERROR(VALUE(REGEXREPLACE(TO_TEXT(General_Ledger_Data!F78), ""[^0-9.]"", """")), 0)"),195.0) -> 195 | G78: =IF(OR(E78=0, F78=0), 0, E78*F78) -> 18525 | H78: =IF(ISNUMBER(General_Ledger_Data!G78), "PASSED CLEAN", "REPAIRED") -> PASSED CLEAN
A79: =General_Ledger_Data!A79 -> TXN-1078 | B79: =General_Ledger_Data!B79 -> 46061 | C79: =General_Ledger_Data!C79 -> 6003-SUPPLY | D79: =IF(OR(ISBLANK(General_Ledger_Data!D79), General_Ledger_Data!D79="#N/A"), "VEND-UNKNOWN", General_Ledger_Data!D79) -> VEND-878 | E79: =IFERROR(__xludf.DUMMYFUNCTION("IFERROR(VALUE(REGEXREPLACE(TO_TEXT(General_Ledger_Data!E79), ""[^0-9.]"", """")), 0)"),0.0) -> 0 | F79: =IFERROR(__xludf.DUMMYFUNCTION("IFERROR(VALUE(REGEXREPLACE(TO_TEXT(General_Ledger_Data!F79), ""[^0-9.]"", """")), 0)"),110.0) -> 110 | G79: =IF(OR(E79=0, F79=0), 0, E79*F79) -> 0 | H79: =IF(ISNUMBER(General_Ledger_Data!G79), "PASSED CLEAN", "REPAIRED") -> REPAIRED
A80: =General_Ledger_Data!A80 -> TXN-1079 | B80: =General_Ledger_Data!B80 -> 46062 | C80: =General_Ledger_Data!C80 -> 6001-OPEX | D80: =IF(OR(ISBLANK(General_Ledger_Data!D80), General_Ledger_Data!D80="#N/A"), "VEND-UNKNOWN", General_Ledger_Data!D80) -> VEND-879 | E80: =IFERROR(__xludf.DUMMYFUNCTION("IFERROR(VALUE(REGEXREPLACE(TO_TEXT(General_Ledger_Data!E80), ""[^0-9.]"", """")), 0)"),145.0) -> 145 | F80: =IFERROR(__xludf.DUMMYFUNCTION("IFERROR(VALUE(REGEXREPLACE(TO_TEXT(General_Ledger_Data!F80), ""[^0-9.]"", """")), 0)"),58.0) -> 58 | G80: =IF(OR(E80=0, F80=0), 0, E80*F80) -> 8410 | H80: =IF(ISNUMBER(General_Ledger_Data!G80), "PASSED CLEAN", "REPAIRED") -> PASSED CLEAN
A81: =General_Ledger_Data!A81 -> TXN-1080 | B81: =General_Ledger_Data!B81 -> 46062 | C81: =General_Ledger_Data!C81 -> 6004-TRAVEL | D81: =IF(OR(ISBLANK(General_Ledger_Data!D81), General_Ledger_Data!D81="#N/A"), "VEND-UNKNOWN", General_Ledger_Data!D81) -> VEND-880 | E81: =IFERROR(__xludf.DUMMYFUNCTION("IFERROR(VALUE(REGEXREPLACE(TO_TEXT(General_Ledger_Data!E81), ""[^0-9.]"", """")), 0)"),220.0) -> 220 | F81: =IFERROR(__xludf.DUMMYFUNCTION("IFERROR(VALUE(REGEXREPLACE(TO_TEXT(General_Ledger_Data!F81), ""[^0-9.]"", """")), 0)"),21.0) -> 21 | G81: =IF(OR(E81=0, F81=0), 0, E81*F81) -> 4620 | H81: =IF(ISNUMBER(General_Ledger_Data!G81), "PASSED CLEAN", "REPAIRED") -> PASSED CLEAN
A82: =General_Ledger_Data!A82 -> TXN-1081 | B82: =General_Ledger_Data!B82 -> 46063 | C82: =General_Ledger_Data!C82 -> 6001-OPEX | D82: =IF(OR(ISBLANK(General_Ledger_Data!D82), General_Ledger_Data!D82="#N/A"), "VEND-UNKNOWN", General_Ledger_Data!D82) -> VEND-881 | E82: =IFERROR(__xludf.DUMMYFUNCTION("IFERROR(VALUE(REGEXREPLACE(TO_TEXT(General_Ledger_Data!E82), ""[^0-9.]"", """")), 0)"),180.0) -> 180 | F82: =IFERROR(__xludf.DUMMYFUNCTION("IFERROR(VALUE(REGEXREPLACE(TO_TEXT(General_Ledger_Data!F82), ""[^0-9.]"", """")), 0)"),38.0) -> 38 | G82: =IF(OR(E82=0, F82=0), 0, E82*F82) -> 6840 | H82: =IF(ISNUMBER(General_Ledger_Data!G82), "PASSED CLEAN", "REPAIRED") -> PASSED CLEAN
A83: =General_Ledger_Data!A83 -> TXN-1082 | B83: =General_Ledger_Data!B83 -> 46063 | C83: =General_Ledger_Data!C83 -> 6002-CAPEX | D83: =IF(OR(ISBLANK(General_Ledger_Data!D83), General_Ledger_Data!D83="#N/A"), "VEND-UNKNOWN", General_Ledger_Data!D83) -> VEND-882 | E83: =IFERROR(__xludf.DUMMYFUNCTION("IFERROR(VALUE(REGEXREPLACE(TO_TEXT(General_Ledger_Data!E83), ""[^0-9.]"", """")), 0)"),85.0) -> 85 | F83: =IFERROR(__xludf.DUMMYFUNCTION("IFERROR(VALUE(REGEXREPLACE(TO_TEXT(General_Ledger_Data!F83), ""[^0-9.]"", """")), 0)"),340.0) -> 340 | G83: =IF(OR(E83=0, F83=0), 0, E83*F83) -> 28900 | H83: =IF(ISNUMBER(General_Ledger_Data!G83), "PASSED CLEAN", "REPAIRED") -> PASSED CLEAN
A84: =General_Ledger_Data!A84 -> TXN-1083 | B84: =General_Ledger_Data!B84 -> 46064 | C84: =General_Ledger_Data!C84 -> 6003-SUPPLY | D84: =IF(OR(ISBLANK(General_Ledger_Data!D84), General_Ledger_Data!D84="#N/A"), "VEND-UNKNOWN", General_Ledger_Data!D84) -> VEND-999 | E84: =IFERROR(__xludf.DUMMYFUNCTION("IFERROR(VALUE(REGEXREPLACE(TO_TEXT(General_Ledger_Data!E84), ""[^0-9.]"", """")), 0)"),0.0) -> 0 | F84: =IFERROR(__xludf.DUMMYFUNCTION("IFERROR(VALUE(REGEXREPLACE(TO_TEXT(General_Ledger_Data!F84), ""[^0-9.]"", """")), 0)"),40.0) -> 40 | G84: =IF(OR(E84=0, F84=0), 0, E84*F84) -> 0 | H84: =IF(ISNUMBER(General_Ledger_Data!G84), "PASSED CLEAN", "REPAIRED") -> REPAIRED
A85: =General_Ledger_Data!A85 -> TXN-1084 | B85: =General_Ledger_Data!B85 -> 46064 | C85: =General_Ledger_Data!C85 -> 6001-OPEX | D85: =IF(OR(ISBLANK(General_Ledger_Data!D85), General_Ledger_Data!D85="#N/A"), "VEND-UNKNOWN", General_Ledger_Data!D85) -> VEND-884 | E85: =IFERROR(__xludf.DUMMYFUNCTION("IFERROR(VALUE(REGEXREPLACE(TO_TEXT(General_Ledger_Data!E85), ""[^0-9.]"", """")), 0)"),250.0) -> 250 | F85: =IFERROR(__xludf.DUMMYFUNCTION("IFERROR(VALUE(REGEXREPLACE(TO_TEXT(General_Ledger_Data!F85), ""[^0-9.]"", """")), 0)"),45.0) -> 45 | G85: =IF(OR(E85=0, F85=0), 0, E85*F85) -> 11250 | H85: =IF(ISNUMBER(General_Ledger_Data!G85), "PASSED CLEAN", "REPAIRED") -> PASSED CLEAN
A86: =General_Ledger_Data!A86 -> TXN-1085 | B86: =General_Ledger_Data!B86 -> 46065 | C86: =General_Ledger_Data!C86 -> 6004-TRAVEL | D86: =IF(OR(ISBLANK(General_Ledger_Data!D86), General_Ledger_Data!D86="#N/A"), "VEND-UNKNOWN", General_Ledger_Data!D86) -> VEND-885 | E86: =IFERROR(__xludf.DUMMYFUNCTION("IFERROR(VALUE(REGEXREPLACE(TO_TEXT(General_Ledger_Data!E86), ""[^0-9.]"", """")), 0)"),40.0) -> 40 | F86: =IFERROR(__xludf.DUMMYFUNCTION("IFERROR(VALUE(REGEXREPLACE(TO_TEXT(General_Ledger_Data!F86), ""[^0-9.]"", """")), 0)"),275.0) -> 275 | G86: =IF(OR(E86=0, F86=0), 0, E86*F86) -> 11000 | H86: =IF(ISNUMBER(General_Ledger_Data!G86), "PASSED CLEAN", "REPAIRED") -> PASSED CLEAN
A87: =General_Ledger_Data!A87 -> TXN-1086 | B87: =General_Ledger_Data!B87 -> 46065 | C87: =General_Ledger_Data!C87 -> 6001-OPEX | D87: =IF(OR(ISBLANK(General_Ledger_Data!D87), General_Ledger_Data!D87="#N/A"), "VEND-UNKNOWN", General_Ledger_Data!D87) -> VEND-886 | E87: =IFERROR(__xludf.DUMMYFUNCTION("IFERROR(VALUE(REGEXREPLACE(TO_TEXT(General_Ledger_Data!E87), ""[^0-9.]"", """")), 0)"),70.0) -> 70 | F87: =IFERROR(__xludf.DUMMYFUNCTION("IFERROR(VALUE(REGEXREPLACE(TO_TEXT(General_Ledger_Data!F87), ""[^0-9.]"", """")), 0)"),0.0) -> 0 | G87: =IF(OR(E87=0, F87=0), 0, E87*F87) -> 0 | H87: =IF(ISNUMBER(General_Ledger_Data!G87), "PASSED CLEAN", "REPAIRED") -> REPAIRED
A88: =General_Ledger_Data!A88 -> TXN-1087 | B88: =General_Ledger_Data!B88 -> 46066 | C88: =General_Ledger_Data!C88 -> 6002-CAPEX | D88: =IF(OR(ISBLANK(General_Ledger_Data!D88), General_Ledger_Data!D88="#N/A"), "VEND-UNKNOWN", General_Ledger_Data!D88) -> VEND-887 | E88: =IFERROR(__xludf.DUMMYFUNCTION("IFERROR(VALUE(REGEXREPLACE(TO_TEXT(General_Ledger_Data!E88), ""[^0-9.]"", """")), 0)"),310.0) -> 310 | F88: =IFERROR(__xludf.DUMMYFUNCTION("IFERROR(VALUE(REGEXREPLACE(TO_TEXT(General_Ledger_Data!F88), ""[^0-9.]"", """")), 0)"),20.0) -> 20 | G88: =IF(OR(E88=0, F88=0), 0, E88*F88) -> 6200 | H88: =IF(ISNUMBER(General_Ledger_Data!G88), "PASSED CLEAN", "REPAIRED") -> PASSED CLEAN
A89: =General_Ledger_Data!A89 -> TXN-1088 | B89: =General_Ledger_Data!B89 -> 46066 | C89: =General_Ledger_Data!C89 -> 6003-SUPPLY | D89: =IF(OR(ISBLANK(General_Ledger_Data!D89), General_Ledger_Data!D89="#N/A"), "VEND-UNKNOWN", General_Ledger_Data!D89) -> VEND-888 | E89: =IFERROR(__xludf.DUMMYFUNCTION("IFERROR(VALUE(REGEXREPLACE(TO_TEXT(General_Ledger_Data!E89), ""[^0-9.]"", """")), 0)"),0.0) -> 0 | F89: =IFERROR(__xludf.DUMMYFUNCTION("IFERROR(VALUE(REGEXREPLACE(TO_TEXT(General_Ledger_Data!F89), ""[^0-9.]"", """")), 0)"),75.0) -> 75 | G89: =IF(OR(E89=0, F89=0), 0, E89*F89) -> 0 | H89: =IF(ISNUMBER(General_Ledger_Data!G89), "PASSED CLEAN", "REPAIRED") -> REPAIRED
A90: =General_Ledger_Data!A90 -> TXN-1089 | B90: =General_Ledger_Data!B90 -> 46067 | C90: =General_Ledger_Data!C90 -> 6001-OPEX | D90: =IF(OR(ISBLANK(General_Ledger_Data!D90), General_Ledger_Data!D90="#N/A"), "VEND-UNKNOWN", General_Ledger_Data!D90) -> VEND-890 | E90: =IFERROR(__xludf.DUMMYFUNCTION("IFERROR(VALUE(REGEXREPLACE(TO_TEXT(General_Ledger_Data!E90), ""[^0-9.]"", """")), 0)"),90.0) -> 90 | F90: =IFERROR(__xludf.DUMMYFUNCTION("IFERROR(VALUE(REGEXREPLACE(TO_TEXT(General_Ledger_Data!F90), ""[^0-9.]"", """")), 0)"),110.0) -> 110 | G90: =IF(OR(E90=0, F90=0), 0, E90*F90) -> 9900 | H90: =IF(ISNUMBER(General_Ledger_Data!G90), "PASSED CLEAN", "REPAIRED") -> PASSED CLEAN
A91: =General_Ledger_Data!A91 -> TXN-1090 | B91: =General_Ledger_Data!B91 -> 46067 | C91: =General_Ledger_Data!C91 -> 6004-TRAVEL | D91: =IF(OR(ISBLANK(General_Ledger_Data!D91), General_Ledger_Data!D91="#N/A"), "VEND-UNKNOWN", General_Ledger_Data!D91) -> VEND-891 | E91: =IFERROR(__xludf.DUMMYFUNCTION("IFERROR(VALUE(REGEXREPLACE(TO_TEXT(General_Ledger_Data!E91), ""[^0-9.]"", """")), 0)"),410.0) -> 410 | F91: =IFERROR(__xludf.DUMMYFUNCTION("IFERROR(VALUE(REGEXREPLACE(TO_TEXT(General_Ledger_Data!F91), ""[^0-9.]"", """")), 0)"),10.0) -> 10 | G91: =IF(OR(E91=0, F91=0), 0, E91*F91) -> 4100 | H91: =IF(ISNUMBER(General_Ledger_Data!G91), "PASSED CLEAN", "REPAIRED") -> PASSED CLEAN
A92: =General_Ledger_Data!A92 -> TXN-1091 | B92: =General_Ledger_Data!B92 -> 46068 | C92: =General_Ledger_Data!C92 -> 6001-OPEX | D92: =IF(OR(ISBLANK(General_Ledger_Data!D92), General_Ledger_Data!D92="#N/A"), "VEND-UNKNOWN", General_Ledger_Data!D92) -> VEND-892 | E92: =IFERROR(__xludf.DUMMYFUNCTION("IFERROR(VALUE(REGEXREPLACE(TO_TEXT(General_Ledger_Data!E92), ""[^0-9.]"", """")), 0)"),105.0) -> 105 | F92: =IFERROR(__xludf.DUMMYFUNCTION("IFERROR(VALUE(REGEXREPLACE(TO_TEXT(General_Ledger_Data!F92), ""[^0-9.]"", """")), 0)"),68.0) -> 68 | G92: =IF(OR(E92=0, F92=0), 0, E92*F92) -> 7140 | H92: =IF(ISNUMBER(General_Ledger_Data!G92), "PASSED CLEAN", "REPAIRED") -> PASSED CLEAN
A93: =General_Ledger_Data!A93 -> TXN-1092 | B93: =General_Ledger_Data!B93 -> 46068 | C93: =General_Ledger_Data!C93 -> 6002-CAPEX | D93: =IF(OR(ISBLANK(General_Ledger_Data!D93), General_Ledger_Data!D93="#N/A"), "VEND-UNKNOWN", General_Ledger_Data!D93) -> VEND-893 | E93: =IFERROR(__xludf.DUMMYFUNCTION("IFERROR(VALUE(REGEXREPLACE(TO_TEXT(General_Ledger_Data!E93), ""[^0-9.]"", """")), 0)"),55.0) -> 55 | F93: =IFERROR(__xludf.DUMMYFUNCTION("IFERROR(VALUE(REGEXREPLACE(TO_TEXT(General_Ledger_Data!F93), ""[^0-9.]"", """")), 0)"),680.0) -> 680 | G93: =IF(OR(E93=0, F93=0), 0, E93*F93) -> 37400 | H93: =IF(ISNUMBER(General_Ledger_Data!G93), "PASSED CLEAN", "REPAIRED") -> PASSED CLEAN
A94: =General_Ledger_Data!A94 -> TXN-1093 | B94: =General_Ledger_Data!B94 -> 46069 | C94: =General_Ledger_Data!C94 -> 6003-SUPPLY | D94: =IF(OR(ISBLANK(General_Ledger_Data!D94), General_Ledger_Data!D94="#N/A"), "VEND-UNKNOWN", General_Ledger_Data!D94) -> VEND-894 | E94: =IFERROR(__xludf.DUMMYFUNCTION("IFERROR(VALUE(REGEXREPLACE(TO_TEXT(General_Ledger_Data!E94), ""[^0-9.]"", """")), 0)"),175.0) -> 175 | F94: =IFERROR(__xludf.DUMMYFUNCTION("IFERROR(VALUE(REGEXREPLACE(TO_TEXT(General_Ledger_Data!F94), ""[^0-9.]"", """")), 0)"),32.0) -> 32 | G94: =IF(OR(E94=0, F94=0), 0, E94*F94) -> 5600 | H94: =IF(ISNUMBER(General_Ledger_Data!G94), "PASSED CLEAN", "REPAIRED") -> PASSED CLEAN
A95: =General_Ledger_Data!A95 -> TXN-1094 | B95: =General_Ledger_Data!B95 -> 46069 | C95: =General_Ledger_Data!C95 -> 6001-OPEX | D95: =IF(OR(ISBLANK(General_Ledger_Data!D95), General_Ledger_Data!D95="#N/A"), "VEND-UNKNOWN", General_Ledger_Data!D95) -> VEND-895 | E95: =IFERROR(__xludf.DUMMYFUNCTION("IFERROR(VALUE(REGEXREPLACE(TO_TEXT(General_Ledger_Data!E95), ""[^0-9.]"", """")), 0)"),0.0) -> 0 | F95: =IFERROR(__xludf.DUMMYFUNCTION("IFERROR(VALUE(REGEXREPLACE(TO_TEXT(General_Ledger_Data!F95), ""[^0-9.]"", """")), 0)"),50.0) -> 50 | G95: =IF(OR(E95=0, F95=0), 0, E95*F95) -> 0 | H95: =IF(ISNUMBER(General_Ledger_Data!G95), "PASSED CLEAN", "REPAIRED") -> REPAIRED
A96: =General_Ledger_Data!A96 -> TXN-1095 | B96: =General_Ledger_Data!B96 -> 46070 | C96: =General_Ledger_Data!C96 -> 6004-TRAVEL | D96: =IF(OR(ISBLANK(General_Ledger_Data!D96), General_Ledger_Data!D96="#N/A"), "VEND-UNKNOWN", General_Ledger_Data!D96) -> VEND-896 | E96: =IFERROR(__xludf.DUMMYFUNCTION("IFERROR(VALUE(REGEXREPLACE(TO_TEXT(General_Ledger_Data!E96), ""[^0-9.]"", """")), 0)"),20.0) -> 20 | F96: =IFERROR(__xludf.DUMMYFUNCTION("IFERROR(VALUE(REGEXREPLACE(TO_TEXT(General_Ledger_Data!F96), ""[^0-9.]"", """")), 0)"),490.0) -> 490 | G96: =IF(OR(E96=0, F96=0), 0, E96*F96) -> 9800 | H96: =IF(ISNUMBER(General_Ledger_Data!G96), "PASSED CLEAN", "REPAIRED") -> PASSED CLEAN
A97: =General_Ledger_Data!A97 -> TXN-1096 | B97: =General_Ledger_Data!B97 -> 46070 | C97: =General_Ledger_Data!C97 -> 6001-OPEX | D97: =IF(OR(ISBLANK(General_Ledger_Data!D97), General_Ledger_Data!D97="#N/A"), "VEND-UNKNOWN", General_Ledger_Data!D97) -> VEND-999 | E97: =IFERROR(__xludf.DUMMYFUNCTION("IFERROR(VALUE(REGEXREPLACE(TO_TEXT(General_Ledger_Data!E97), ""[^0-9.]"", """")), 0)"),250.0) -> 250 | F97: =IFERROR(__xludf.DUMMYFUNCTION("IFERROR(VALUE(REGEXREPLACE(TO_TEXT(General_Ledger_Data!F97), ""[^0-9.]"", """")), 0)"),0.0) -> 0 | G97: =IF(OR(E97=0, F97=0), 0, E97*F97) -> 0 | H97: =IF(ISNUMBER(General_Ledger_Data!G97), "PASSED CLEAN", "REPAIRED") -> REPAIRED
A98: =General_Ledger_Data!A98 -> TXN-1097 | B98: =General_Ledger_Data!B98 -> 46071 | C98: =General_Ledger_Data!C98 -> 6002-CAPEX | D98: =IF(OR(ISBLANK(General_Ledger_Data!D98), General_Ledger_Data!D98="#N/A"), "VEND-UNKNOWN", General_Ledger_Data!D98) -> VEND-898 | E98: =IFERROR(__xludf.DUMMYFUNCTION("IFERROR(VALUE(REGEXREPLACE(TO_TEXT(General_Ledger_Data!E98), ""[^0-9.]"", """")), 0)"),115.0) -> 115 | F98: =IFERROR(__xludf.DUMMYFUNCTION("IFERROR(VALUE(REGEXREPLACE(TO_TEXT(General_Ledger_Data!F98), ""[^0-9.]"", """")), 0)"),150.0) -> 150 | G98: =IF(OR(E98=0, F98=0), 0, E98*F98) -> 17250 | H98: =IF(ISNUMBER(General_Ledger_Data!G98), "PASSED CLEAN", "REPAIRED") -> PASSED CLEAN
A99: =General_Ledger_Data!A99 -> TXN-1098 | B99: =General_Ledger_Data!B99 -> 46071 | C99: =General_Ledger_Data!C99 -> 6003-SUPPLY | D99: =IF(OR(ISBLANK(General_Ledger_Data!D99), General_Ledger_Data!D99="#N/A"), "VEND-UNKNOWN", General_Ledger_Data!D99) -> VEND-899 | E99: =IFERROR(__xludf.DUMMYFUNCTION("IFERROR(VALUE(REGEXREPLACE(TO_TEXT(General_Ledger_Data!E99), ""[^0-9.]"", """")), 0)"),0.0) -> 0 | F99: =IFERROR(__xludf.DUMMYFUNCTION("IFERROR(VALUE(REGEXREPLACE(TO_TEXT(General_Ledger_Data!F99), ""[^0-9.]"", """")), 0)"),140.0) -> 140 | G99: =IF(OR(E99=0, F99=0), 0, E99*F99) -> 0 | H99: =IF(ISNUMBER(General_Ledger_Data!G99), "PASSED CLEAN", "REPAIRED") -> REPAIRED
A100: =General_Ledger_Data!A100 -> TXN-1099 | B100: =General_Ledger_Data!B100 -> 46072 | C100: =General_Ledger_Data!C100 -> 6001-OPEX | D100: =IF(OR(ISBLANK(General_Ledger_Data!D100), General_Ledger_Data!D100="#N/A"), "VEND-UNKNOWN", General_Ledger_Data!D100) -> VEND-900 | E100: =IFERROR(__xludf.DUMMYFUNCTION("IFERROR(VALUE(REGEXREPLACE(TO_TEXT(General_Ledger_Data!E100), ""[^0-9.]"", """")), 0)"),140.0) -> 140 | F100: =IFERROR(__xludf.DUMMYFUNCTION("IFERROR(VALUE(REGEXREPLACE(TO_TEXT(General_Ledger_Data!F100), ""[^0-9.]"", """")), 0)"),55.0) -> 55 | G100: =IF(OR(E100=0, F100=0), 0, E100*F100) -> 7700 | H100: =IF(ISNUMBER(General_Ledger_Data!G100), "PASSED CLEAN", "REPAIRED") -> PASSED CLEAN
...

Sheet Reconciliation_Matrix
A1: Txn_ID | B1: Repaired_Cost | C1: Subledger_Balance | D1: Absolute_Variance | E1: Tolerance_Threshold | F1: Reconciliation_Status
A2: =General_Ledger_Data!A2 -> TXN-1001 | B2: =Formula_Repair_Engine!G2 -> 6750 | C2: =General_Ledger_Data!H2 -> 6750 | D2: =ABS(B2-C2) -> 0 | E2: =0.04 -> 0.04 | F2: =IF(D2<=E2, "MATCHED", "VARIANCE DETECTED") -> MATCHED
A3: =General_Ledger_Data!A3 -> TXN-1002 | B3: =Formula_Repair_Engine!G3 -> 0 | C3: =General_Ledger_Data!H3 -> 3200 | D3: =ABS(B3-C3) -> 3200 | E3: =0.04 -> 0.04 | F3: =IF(D3<=E3, "MATCHED", "VARIANCE DETECTED") -> VARIANCE DETECTED
A4: =General_Ledger_Data!A4 -> TXN-1003 | B4: =Formula_Repair_Engine!G4 -> 0 | C4: =General_Ledger_Data!H4 -> 0 | D4: =ABS(B4-C4) -> 0 | E4: =0.04 -> 0.04 | F4: =IF(D4<=E4, "MATCHED", "VARIANCE DETECTED") -> MATCHED
A5: =General_Ledger_Data!A5 -> TXN-1004 | B5: =Formula_Repair_Engine!G5 -> 3100 | C5: =General_Ledger_Data!H5 -> 3100 | D5: =ABS(B5-C5) -> 0 | E5: =0.04 -> 0.04 | F5: =IF(D5<=E5, "MATCHED", "VARIANCE DETECTED") -> MATCHED
A6: =General_Ledger_Data!A6 -> TXN-1005 | B6: =Formula_Repair_Engine!G6 -> 15500 | C6: =General_Ledger_Data!H6 -> 15500 | D6: =ABS(B6-C6) -> 0 | E6: =0.04 -> 0.04 | F6: =IF(D6<=E6, "MATCHED", "VARIANCE DETECTED") -> MATCHED
A7: =General_Ledger_Data!A7 -> TXN-1006 | B7: =Formula_Repair_Engine!G7 -> 0 | C7: =General_Ledger_Data!H7 -> 1875 | D7: =ABS(B7-C7) -> 1875 | E7: =0.04 -> 0.04 | F7: =IF(D7<=E7, "MATCHED", "VARIANCE DETECTED") -> VARIANCE DETECTED
A8: =General_Ledger_Data!A8 -> TXN-1007 | B8: =Formula_Repair_Engine!G8 -> 11400 | C8: =General_Ledger_Data!H8 -> 11400 | D8: =ABS(B8-C8) -> 0 | E8: =0.04 -> 0.04 | F8: =IF(D8<=E8, "MATCHED", "VARIANCE DETECTED") -> MATCHED
A9: =General_Ledger_Data!A9 -> TXN-1008 | B9: =Formula_Repair_Engine!G9 -> 0 | C9: =General_Ledger_Data!H9 -> 0 | D9: =ABS(B9-C9) -> 0 | E9: =0.04 -> 0.04 | F9: =IF(D9<=E9, "MATCHED", "VARIANCE DETECTED") -> MATCHED
A10: =General_Ledger_Data!A10 -> TXN-1009 | B10: =Formula_Repair_Engine!G10 -> 0 | C10: =General_Ledger_Data!H10 -> 1800 | D10: =ABS(B10-C10) -> 1800 | E10: =0.04 -> 0.04 | F10: =IF(D10<=E10, "MATCHED", "VARIANCE DETECTED") -> VARIANCE DETECTED
A11: =General_Ledger_Data!A11 -> TXN-1010 | B11: =Formula_Repair_Engine!G11 -> 6250 | C11: =General_Ledger_Data!H11 -> 6250 | D11: =ABS(B11-C11) -> 0 | E11: =0.04 -> 0.04 | F11: =IF(D11<=E11, "MATCHED", "VARIANCE DETECTED") -> MATCHED
A12: =General_Ledger_Data!A12 -> TXN-1011 | B12: =Formula_Repair_Engine!G12 -> 4500 | C12: =General_Ledger_Data!H12 -> 4500 | D12: =ABS(B12-C12) -> 0 | E12: =0.04 -> 0.04 | F12: =IF(D12<=E12, "MATCHED", "VARIANCE DETECTED") -> MATCHED
A13: =General_Ledger_Data!A13 -> TXN-1012 | B13: =Formula_Repair_Engine!G13 -> 12500 | C13: =General_Ledger_Data!H13 -> 12500.05 | D13: =ABS(B13-C13) -> 0.05 | E13: =0.04 -> 0.04 | F13: =IF(D13<=E13, "MATCHED", "VARIANCE DETECTED") -> VARIANCE DETECTED
... A101: =General_Ledger_Data!A101 -> TXN-1100 | B101: =Formula_Repair_Engine!G101 -> 4500 | C101: =General_Ledger_Data!H101 -> 4500 | D101: =ABS(B101-C101) -> 0 | E101: =0.04 -> 0.04 | F101: =IF(D101<=E101, "MATCHED", "VARIANCE DETECTED") -> MATCHED

Sheet Executive_Dashboard
A1: ENTERPRISE FINANCIAL AUDIT & REPAIR EXECUTIVE CONSOLE
A3: Total Transactions Audited | B3: Errors Trapped & Repaired | C3: Reconciliation Variances | D3: System Health Stability Score
A4: =COUNTA(General_Ledger_Data!A2:A101) -> 100 | B4: =COUNTIF(Formula_Repair_Engine!H2:H101, "REPAIRED") -> 34 | C4: =COUNTIF(Reconciliation_Matrix!F2:F101, "VARIANCE DETECTED") -> 27 | D4: =(1 - (B4 / A4)) -> 0.66
